{
"meta":{"test_sets":[],"test_metrics":[],"learn_metrics":[{"best_value":"Min","name":"RMSE"}],"launch_mode":"Train","parameters":"","iteration_count":1000,"learn_sets":["learn"],"name":"experiment"},
"iterations":[
{"learn":[0.1379702218],"iteration":0,"passed_time":0.05254531854,"remaining_time":52.49277322},
{"learn":[0.1348849455],"iteration":1,"passed_time":0.0534902265,"remaining_time":26.69162302},
{"learn":[0.1319799575],"iteration":2,"passed_time":0.05454345746,"remaining_time":18.12660903},
{"learn":[0.1291662379],"iteration":3,"passed_time":0.0559740345,"remaining_time":13.93753459},
{"learn":[0.1264664561],"iteration":4,"passed_time":0.05665642722,"remaining_time":11.27462902},
{"learn":[0.1237522466],"iteration":5,"passed_time":0.05757918502,"remaining_time":9.538951651},
{"learn":[0.1213122296],"iteration":6,"passed_time":0.05845899362,"remaining_time":8.292825809},
{"learn":[0.1190279124],"iteration":7,"passed_time":0.05932909548,"remaining_time":7.356807839},
{"learn":[0.1167631453],"iteration":8,"passed_time":0.06019346618,"remaining_time":6.627969443},
{"learn":[0.1143729418],"iteration":9,"passed_time":0.06103463561,"remaining_time":6.042428926},
{"learn":[0.1121523051],"iteration":10,"passed_time":0.06188666845,"remaining_time":5.5641741},
{"learn":[0.1099170411],"iteration":11,"passed_time":0.0627603259,"remaining_time":5.167266832},
{"learn":[0.1077636469],"iteration":12,"passed_time":0.0636292633,"remaining_time":4.830929452},
{"learn":[0.1056441622],"iteration":13,"passed_time":0.06454863774,"remaining_time":4.546068344},
{"learn":[0.1036913831],"iteration":14,"passed_time":0.0654671544,"remaining_time":4.299009806},
{"learn":[0.1016881248],"iteration":15,"passed_time":0.06634333408,"remaining_time":4.080115046},
{"learn":[0.09976627341],"iteration":16,"passed_time":0.06731094665,"remaining_time":3.892156503},
{"learn":[0.09794347749],"iteration":17,"passed_time":0.06829903492,"remaining_time":3.726091794},
{"learn":[0.0962275043],"iteration":18,"passed_time":0.06926820417,"remaining_time":3.576426752},
{"learn":[0.09455934146],"iteration":19,"passed_time":0.07014022937,"remaining_time":3.436871239},
{"learn":[0.09297955212],"iteration":20,"passed_time":0.07098172769,"remaining_time":3.309100543},
{"learn":[0.09159346454],"iteration":21,"passed_time":0.07206298553,"remaining_time":3.203527266},
{"learn":[0.09006554327],"iteration":22,"passed_time":0.07301132018,"remaining_time":3.101393905},
{"learn":[0.08870953188],"iteration":23,"passed_time":0.07457309816,"remaining_time":3.032639325},
{"learn":[0.08731088818],"iteration":24,"passed_time":0.07601771974,"remaining_time":2.96469107},
{"learn":[0.08609353176],"iteration":25,"passed_time":0.07732512366,"remaining_time":2.896718094},
{"learn":[0.08478855625],"iteration":26,"passed_time":0.0784351517,"remaining_time":2.826570467},
{"learn":[0.0835301315],"iteration":27,"passed_time":0.07931067583,"remaining_time":2.753213461},
{"learn":[0.0823653462],"iteration":28,"passed_time":0.08020489786,"remaining_time":2.685481235},
{"learn":[0.08109904752],"iteration":29,"passed_time":0.08104874398,"remaining_time":2.620576055},
{"learn":[0.07980253427],"iteration":30,"passed_time":0.08192100696,"remaining_time":2.560692121},
{"learn":[0.07852181727],"iteration":31,"passed_time":0.08292091977,"remaining_time":2.508357823},
{"learn":[0.07750704165],"iteration":32,"passed_time":0.08390059131,"remaining_time":2.45854157},
{"learn":[0.07638489343],"iteration":33,"passed_time":0.08507180424,"remaining_time":2.417040085},
{"learn":[0.07542552074],"iteration":34,"passed_time":0.08605262801,"remaining_time":2.372593887},
{"learn":[0.07433796373],"iteration":35,"passed_time":0.08688267625,"remaining_time":2.326524997},
{"learn":[0.07334152424],"iteration":36,"passed_time":0.0877020833,"remaining_time":2.282624492},
{"learn":[0.07241708273],"iteration":37,"passed_time":0.08843697307,"remaining_time":2.238851792},
{"learn":[0.07145029354],"iteration":38,"passed_time":0.08920790088,"remaining_time":2.198174173},
{"learn":[0.07050313813],"iteration":39,"passed_time":0.08993776728,"remaining_time":2.158506415},
{"learn":[0.06972271423],"iteration":40,"passed_time":0.09065959029,"remaining_time":2.120549929},
{"learn":[0.06886196073],"iteration":41,"passed_time":0.09138265219,"remaining_time":2.084394781},
{"learn":[0.06811807327],"iteration":42,"passed_time":0.09234768363,"remaining_time":2.055272866},
{"learn":[0.06732665791],"iteration":43,"passed_time":0.09316978181,"remaining_time":2.024325259},
{"learn":[0.0666181577],"iteration":44,"passed_time":0.09396472646,"remaining_time":1.994140306},
{"learn":[0.06589636708],"iteration":45,"passed_time":0.09468894504,"remaining_time":1.963766382},
{"learn":[0.06520703171],"iteration":46,"passed_time":0.09539973241,"remaining_time":1.934381808},
{"learn":[0.06451500229],"iteration":47,"passed_time":0.09632914026,"remaining_time":1.910527948},
{"learn":[0.06391675182],"iteration":48,"passed_time":0.09718427201,"remaining_time":1.886168218},
{"learn":[0.06322426628],"iteration":49,"passed_time":0.09815527016,"remaining_time":1.864950133},
{"learn":[0.06262997579],"iteration":50,"passed_time":0.09964953432,"remaining_time":1.854262903},
{"learn":[0.0620696437],"iteration":51,"passed_time":0.1011564875,"remaining_time":1.844160579},
{"learn":[0.06150317864],"iteration":52,"passed_time":0.102481566,"remaining_time":1.831132886},
{"learn":[0.06101006586],"iteration":53,"passed_time":0.1035323069,"remaining_time":1.813732636},
{"learn":[0.06046598023],"iteration":54,"passed_time":0.1047333812,"remaining_time":1.799509913},
{"learn":[0.05990940009],"iteration":55,"passed_time":0.1056415522,"remaining_time":1.780814737},
{"learn":[0.05937875799],"iteration":56,"passed_time":0.1066936731,"remaining_time":1.765125154},
{"learn":[0.05902806931],"iteration":57,"passed_time":0.1075211647,"remaining_time":1.74629202},
{"learn":[0.05855395128],"iteration":58,"passed_time":0.1084484125,"remaining_time":1.729660274},
{"learn":[0.05813084429],"iteration":59,"passed_time":0.1093406101,"remaining_time":1.713002892},
{"learn":[0.05765136271],"iteration":60,"passed_time":0.1101630161,"remaining_time":1.695788067},
{"learn":[0.05723437485],"iteration":61,"passed_time":0.1109492618,"remaining_time":1.67855496},
{"learn":[0.05683320997],"iteration":62,"passed_time":0.1119833559,"remaining_time":1.66553023},
{"learn":[0.05645001334],"iteration":63,"passed_time":0.1128046463,"remaining_time":1.649767952},
{"learn":[0.05605581854],"iteration":64,"passed_time":0.1143303918,"remaining_time":1.644598713},
{"learn":[0.05571199489],"iteration":65,"passed_time":0.1152765487,"remaining_time":1.631337825},
{"learn":[0.05543996707],"iteration":66,"passed_time":0.1159220133,"remaining_time":1.61425729},
{"learn":[0.05510402532],"iteration":67,"passed_time":0.1167163391,"remaining_time":1.599700412},
{"learn":[0.0547423184],"iteration":68,"passed_time":0.1174580845,"remaining_time":1.584832995},
{"learn":[0.05437181299],"iteration":69,"passed_time":0.1181781797,"remaining_time":1.57008153},
{"learn":[0.05410999036],"iteration":70,"passed_time":0.1189047061,"remaining_time":1.555809464},
{"learn":[0.05372835298],"iteration":71,"passed_time":0.1196238613,"remaining_time":1.541818657},
{"learn":[0.05343867444],"iteration":72,"passed_time":0.1203174774,"remaining_time":1.527867145},
{"learn":[0.05320957307],"iteration":73,"passed_time":0.1210332682,"remaining_time":1.514551437},
{"learn":[0.0529702635],"iteration":74,"passed_time":0.1217567601,"remaining_time":1.501666708},
{"learn":[0.05269317879],"iteration":75,"passed_time":0.1224513829,"remaining_time":1.488751023},
{"learn":[0.05242411167],"iteration":76,"passed_time":0.123170627,"remaining_time":1.476447905},
{"learn":[0.05214021675],"iteration":77,"passed_time":0.1240241621,"remaining_time":1.466029198},
{"learn":[0.05189116424],"iteration":78,"passed_time":0.1247634907,"remaining_time":1.454521202},
{"learn":[0.05161543643],"iteration":79,"passed_time":0.1258162217,"remaining_time":1.44688655},
{"learn":[0.05145797526],"iteration":80,"passed_time":0.1269380998,"remaining_time":1.440198935},
{"learn":[0.05123498951],"iteration":81,"passed_time":0.1282510205,"remaining_time":1.435785814},
{"learn":[0.05106224208],"iteration":82,"passed_time":0.1295218997,"remaining_time":1.430982916},
{"learn":[0.05077720627],"iteration":83,"passed_time":0.1306735236,"remaining_time":1.424963662},
{"learn":[0.05057680113],"iteration":84,"passed_time":0.1318707534,"remaining_time":1.419549874},
{"learn":[0.0504175791],"iteration":85,"passed_time":0.1327268551,"remaining_time":1.41060867},
{"learn":[0.05019553024],"iteration":86,"passed_time":0.1335531844,"remaining_time":1.40154089},
{"learn":[0.04999015318],"iteration":87,"passed_time":0.1343004954,"remaining_time":1.391841498},
{"learn":[0.04974503864],"iteration":88,"passed_time":0.1350044072,"remaining_time":1.381899044},
{"learn":[0.04956116751],"iteration":89,"passed_time":0.1356974155,"remaining_time":1.372051646},
{"learn":[0.04942031112],"iteration":90,"passed_time":0.1363920117,"remaining_time":1.362421303},
{"learn":[0.04928887252],"iteration":91,"passed_time":0.1370749089,"remaining_time":1.352869753},
{"learn":[0.04916551448],"iteration":92,"passed_time":0.1377734095,"remaining_time":1.343661101},
{"learn":[0.04897670206],"iteration":93,"passed_time":0.1384639811,"remaining_time":1.334557095},
{"learn":[0.04875280253],"iteration":94,"passed_time":0.1391567128,"remaining_time":1.325650791},
{"learn":[0.04865453254],"iteration":95,"passed_time":0.1396685499,"remaining_time":1.315212178},
{"learn":[0.04840129291],"iteration":96,"passed_time":0.1403628849,"remaining_time":1.306677166},
{"learn":[0.04824862641],"iteration":97,"passed_time":0.1415023576,"remaining_time":1.302399251},
{"learn":[0.04813583217],"iteration":98,"passed_time":0.142428281,"remaining_time":1.296241224},
{"learn":[0.04803961341],"iteration":99,"passed_time":0.1435044032,"remaining_time":1.291539629},
{"learn":[0.04792712862],"iteration":100,"passed_time":0.1447385844,"remaining_time":1.288316707},
{"learn":[0.04773348147],"iteration":101,"passed_time":0.1460111025,"remaining_time":1.285470295},
{"learn":[0.04760799911],"iteration":102,"passed_time":0.1468753165,"remaining_time":1.27909863},
{"learn":[0.04740172228],"iteration":103,"passed_time":0.1476813657,"remaining_time":1.272331766},
{"learn":[0.04732233298],"iteration":104,"passed_time":0.1484495146,"remaining_time":1.265355386},
{"learn":[0.04716898617],"iteration":105,"passed_time":0.1491490841,"remaining_time":1.257917747},
{"learn":[0.04707100642],"iteration":106,"passed_time":0.1498531659,"remaining_time":1.250643712},
{"learn":[0.04689846468],"iteration":107,"passed_time":0.1505703933,"remaining_time":1.243599915},
{"learn":[0.04679661809],"iteration":108,"passed_time":0.1517019048,"remaining_time":1.24005869},
{"learn":[0.04670377599],"iteration":109,"passed_time":0.152674213,"remaining_time":1.235273178},
{"learn":[0.04655926571],"iteration":110,"passed_time":0.1541751539,"remaining_time":1.234790196},
{"learn":[0.04643921843],"iteration":111,"passed_time":0.1565670623,"remaining_time":1.241353137},
{"learn":[0.04634475435],"iteration":112,"passed_time":0.157702035,"remaining_time":1.237891195},
{"learn":[0.04627413633],"iteration":113,"passed_time":0.159302711,"remaining_time":1.238089491},
{"learn":[0.04619641706],"iteration":114,"passed_time":0.1601924175,"remaining_time":1.232785126},
{"learn":[0.04602764611],"iteration":115,"passed_time":0.1610300269,"remaining_time":1.22715986},
{"learn":[0.04594361019],"iteration":116,"passed_time":0.1618746563,"remaining_time":1.221669415},
{"learn":[0.04580568821],"iteration":117,"passed_time":0.1626248762,"remaining_time":1.215552041},
{"learn":[0.04567505156],"iteration":118,"passed_time":0.1633477381,"remaining_time":1.20932233},
{"learn":[0.04555015838],"iteration":119,"passed_time":0.1640642566,"remaining_time":1.203137882},
{"learn":[0.04543431078],"iteration":120,"passed_time":0.164780683,"remaining_time":1.197043143},
{"learn":[0.04528307307],"iteration":121,"passed_time":0.1656489881,"remaining_time":1.192129603},
{"learn":[0.04514143636],"iteration":122,"passed_time":0.1663933469,"remaining_time":1.186398091},
{"learn":[0.04506660062],"iteration":123,"passed_time":0.1671217299,"remaining_time":1.180634157},
{"learn":[0.04497176049],"iteration":124,"passed_time":0.1678414062,"remaining_time":1.174889844},
{"learn":[0.04487868003],"iteration":125,"passed_time":0.1685650126,"remaining_time":1.169252548},
{"learn":[0.04477988931],"iteration":126,"passed_time":0.1692784789,"remaining_time":1.16362293},
{"learn":[0.04467562213],"iteration":127,"passed_time":0.170223868,"remaining_time":1.1596501},
{"learn":[0.0446065164],"iteration":128,"passed_time":0.1712484309,"remaining_time":1.156258786},
{"learn":[0.04457433281],"iteration":129,"passed_time":0.1717954582,"remaining_time":1.149708067},
{"learn":[0.04451393738],"iteration":130,"passed_time":0.172732935,"remaining_time":1.145839088},
{"learn":[0.04440842651],"iteration":131,"passed_time":0.1738765366,"remaining_time":1.143369953},
{"learn":[0.04429696516],"iteration":132,"passed_time":0.1747448318,"remaining_time":1.139126084},
{"learn":[0.04418969714],"iteration":133,"passed_time":0.1755747801,"remaining_time":1.134684773},
{"learn":[0.04412945741],"iteration":134,"passed_time":0.1763357834,"remaining_time":1.129855204},
{"learn":[0.04398435882],"iteration":135,"passed_time":0.1770386629,"remaining_time":1.124716211},
{"learn":[0.04388766086],"iteration":136,"passed_time":0.1775587422,"remaining_time":1.118490471},
{"learn":[0.043795581],"iteration":137,"passed_time":0.1782427738,"remaining_time":1.113371529},
{"learn":[0.04372230488],"iteration":138,"passed_time":0.1792630701,"remaining_time":1.110399305},
{"learn":[0.04367132246],"iteration":139,"passed_time":0.1799417995,"remaining_time":1.105356768},
{"learn":[0.04349005791],"iteration":140,"passed_time":0.181133987,"remaining_time":1.103504219},
{"learn":[0.04340813985],"iteration":141,"passed_time":0.1820284057,"remaining_time":1.099861775},
{"learn":[0.04336099803],"iteration":142,"passed_time":0.1823763016,"remaining_time":1.092982451},
{"learn":[0.0432605388],"iteration":143,"passed_time":0.1831656106,"remaining_time":1.088817796},
{"learn":[0.04313785886],"iteration":144,"passed_time":0.18414738,"remaining_time":1.085834551},
{"learn":[0.04304571258],"iteration":145,"passed_time":0.1852750437,"remaining_time":1.083732105},
{"learn":[0.0430054489],"iteration":146,"passed_time":0.1866503059,"remaining_time":1.083079666},
{"learn":[0.0429571858],"iteration":147,"passed_time":0.1882587142,"remaining_time":1.083759625},
{"learn":[0.0428823847],"iteration":148,"passed_time":0.189348411,"remaining_time":1.081446294},
{"learn":[0.04278026412],"iteration":149,"passed_time":0.1903874974,"remaining_time":1.078862485},
{"learn":[0.04268779624],"iteration":150,"passed_time":0.1912667204,"remaining_time":1.075400302},
{"learn":[0.04263024249],"iteration":151,"passed_time":0.1922291241,"remaining_time":1.072436166},
{"learn":[0.04251218952],"iteration":152,"passed_time":0.1930420189,"remaining_time":1.068670523},
{"learn":[0.04245119032],"iteration":153,"passed_time":0.193898694,"remaining_time":1.065183734},
{"learn":[0.04230069322],"iteration":154,"passed_time":0.1949000745,"remaining_time":1.062519761},
{"learn":[0.04214120015],"iteration":155,"passed_time":0.1957636097,"remaining_time":1.059131324},
{"learn":[0.04200866032],"iteration":156,"passed_time":0.1965591855,"remaining_time":1.055410149},
{"learn":[0.04197980424],"iteration":157,"passed_time":0.1973059798,"remaining_time":1.051466044},
{"learn":[0.04190304463],"iteration":158,"passed_time":0.1979973659,"remaining_time":1.047269086},
{"learn":[0.04178049546],"iteration":159,"passed_time":0.1987055721,"remaining_time":1.043204254},
{"learn":[0.04169010653],"iteration":160,"passed_time":0.1997306051,"remaining_time":1.04083216},
{"learn":[0.04160903121],"iteration":161,"passed_time":0.2006155748,"remaining_time":1.037752171},
{"learn":[0.04154587682],"iteration":162,"passed_time":0.2019617502,"remaining_time":1.037067392},
{"learn":[0.04150221632],"iteration":163,"passed_time":0.2028747068,"remaining_time":1.034166188},
{"learn":[0.04146337181],"iteration":164,"passed_time":0.2036947116,"remaining_time":1.030818692},
{"learn":[0.04136540504],"iteration":165,"passed_time":0.2046301473,"remaining_time":1.028081583},
{"learn":[0.04131139076],"iteration":166,"passed_time":0.2056518369,"remaining_time":1.025796288},
{"learn":[0.04123821039],"iteration":167,"passed_time":0.2066401163,"remaining_time":1.023360576},
{"learn":[0.04118295517],"iteration":168,"passed_time":0.2078811542,"remaining_time":1.022184847},
{"learn":[0.04111972287],"iteration":169,"passed_time":0.2097146874,"remaining_time":1.023901121},
{"learn":[0.0410730438],"iteration":170,"passed_time":0.2111993738,"remaining_time":1.023884683},
{"learn":[0.04105151935],"iteration":171,"passed_time":0.2120514122,"remaining_time":1.020805635},
{"learn":[0.04095978538],"iteration":172,"passed_time":0.212960901,"remaining_time":1.018026966},
{"learn":[0.040844224],"iteration":173,"passed_time":0.2139791272,"remaining_time":1.015785972},
{"learn":[0.0407616765],"iteration":174,"passed_time":0.2150007746,"remaining_time":1.01357508},
{"learn":[0.04066333397],"iteration":175,"passed_time":0.2167429462,"remaining_time":1.014751066},
{"learn":[0.04055074012],"iteration":176,"passed_time":0.2177546457,"remaining_time":1.01249759},
{"learn":[0.04047061621],"iteration":177,"passed_time":0.2186210753,"remaining_time":1.009587213},
{"learn":[0.0403726817],"iteration":178,"passed_time":0.219430959,"remaining_time":1.00644032},
{"learn":[0.04026527955],"iteration":179,"passed_time":0.2203127065,"remaining_time":1.003646774},
{"learn":[0.04018126589],"iteration":180,"passed_time":0.2210722386,"remaining_time":1.000321345},
{"learn":[0.04015969296],"iteration":181,"passed_time":0.2217736393,"remaining_time":0.9967628403},
{"learn":[0.04009329639],"iteration":182,"passed_time":0.2227287106,"remaining_time":0.9943680688},
{"learn":[0.04004890289],"iteration":183,"passed_time":0.2240174755,"remaining_time":0.9934688046},
{"learn":[0.03997073188],"iteration":184,"passed_time":0.2248401693,"remaining_time":0.9905120971},
{"learn":[0.03994332476],"iteration":185,"passed_time":0.2256451829,"remaining_time":0.9875009617},
{"learn":[0.03983965168],"iteration":186,"passed_time":0.2263805193,"remaining_time":0.9842104931},
{"learn":[0.03974994771],"iteration":187,"passed_time":0.22708205,"remaining_time":0.9808011945},
{"learn":[0.03970178862],"iteration":188,"passed_time":0.2278078208,"remaining_time":0.9775245643},
{"learn":[0.03956372632],"iteration":189,"passed_time":0.2288464094,"remaining_time":0.975608377},
{"learn":[0.039518732],"iteration":190,"passed_time":0.2297007789,"remaining_time":0.9729211003},
{"learn":[0.03943845439],"iteration":191,"passed_time":0.2309720215,"remaining_time":0.9720072571},
{"learn":[0.03938479297],"iteration":192,"passed_time":0.2323180479,"remaining_time":0.9714024076},
{"learn":[0.03934368145],"iteration":193,"passed_time":0.233486303,"remaining_time":0.9700513415},
{"learn":[0.03929617615],"iteration":194,"passed_time":0.2349903362,"remaining_time":0.9700883108},
{"learn":[0.03920777803],"iteration":195,"passed_time":0.2366573694,"remaining_time":0.9707781886},
{"learn":[0.03911595592],"iteration":196,"passed_time":0.2387332777,"remaining_time":0.9731107717},
{"learn":[0.03905096858],"iteration":197,"passed_time":0.2399053296,"remaining_time":0.971737749},
{"learn":[0.038989835],"iteration":198,"passed_time":0.2408031394,"remaining_time":0.9692628877},
{"learn":[0.0389313108],"iteration":199,"passed_time":0.2416878036,"remaining_time":0.9667512143},
{"learn":[0.03882432949],"iteration":200,"passed_time":0.2425800323,"remaining_time":0.9642857999},
{"learn":[0.03877433526],"iteration":201,"passed_time":0.2437679675,"remaining_time":0.963004149},
{"learn":[0.03868061572],"iteration":202,"passed_time":0.2471140462,"remaining_time":0.9701965264},
{"learn":[0.03865376147],"iteration":203,"passed_time":0.2500280374,"remaining_time":0.9755995967},
{"learn":[0.03858323539],"iteration":204,"passed_time":0.2518777208,"remaining_time":0.9767940878},
{"learn":[0.03850808966],"iteration":205,"passed_time":0.253262023,"remaining_time":0.9761652732},
{"learn":[0.03840995374],"iteration":206,"passed_time":0.2542679392,"remaining_time":0.9740795931},
{"learn":[0.03838390695],"iteration":207,"passed_time":0.2553970485,"remaining_time":0.9724733769},
{"learn":[0.03825753671],"iteration":208,"passed_time":0.2564366638,"remaining_time":0.9705330194},
{"learn":[0.03817382652],"iteration":209,"passed_time":0.2595247651,"remaining_time":0.9763074495},
{"learn":[0.03804416794],"iteration":210,"passed_time":0.2620827836,"remaining_time":0.9800157169},
{"learn":[0.03800388056],"iteration":211,"passed_time":0.2637510057,"remaining_time":0.9803575117},
{"learn":[0.03794239585],"iteration":212,"passed_time":0.2656382416,"remaining_time":0.9814896532},
{"learn":[0.03787061517],"iteration":213,"passed_time":0.2669343876,"remaining_time":0.980422564},
{"learn":[0.03782407427],"iteration":214,"passed_time":0.268815389,"remaining_time":0.9814887461},
{"learn":[0.03770584107],"iteration":215,"passed_time":0.2696914176,"remaining_time":0.9788799602},
{"learn":[0.03763069316],"iteration":216,"passed_time":0.2704703722,"remaining_time":0.9759368728},
{"learn":[0.03756432458],"iteration":217,"passed_time":0.2715493866,"remaining_time":0.9740900016},
{"learn":[0.03750810301],"iteration":218,"passed_time":0.2727581232,"remaining_time":0.9727127589},
{"learn":[0.03735510785],"iteration":219,"passed_time":0.2751777107,"remaining_time":0.9756300652},
{"learn":[0.03731136026],"iteration":220,"passed_time":0.2771500483,"remaining_time":0.9769225686},
{"learn":[0.03715385063],"iteration":221,"passed_time":0.2782065171,"remaining_time":0.9749759924},
{"learn":[0.0370920646],"iteration":222,"passed_time":0.2790399554,"remaining_time":0.9722602929},
{"learn":[0.0370600178],"iteration":223,"passed_time":0.2798367289,"remaining_time":0.9694343823},
{"learn":[0.03696008373],"iteration":224,"passed_time":0.2805809065,"remaining_time":0.9664453447},
{"learn":[0.03684383388],"iteration":225,"passed_time":0.2812798349,"remaining_time":0.9633212046},
{"learn":[0.03683660617],"iteration":226,"passed_time":0.2819458853,"remaining_time":0.9601064729},
{"learn":[0.03680265221],"iteration":227,"passed_time":0.2826286658,"remaining_time":0.9569707456},
{"learn":[0.03664363451],"iteration":228,"passed_time":0.2833424721,"remaining_time":0.9539608995},
{"learn":[0.03655416419],"iteration":229,"passed_time":0.2845578576,"remaining_time":0.9526502188},
{"learn":[0.03641672271],"iteration":230,"passed_time":0.2855743805,"remaining_time":0.9506783489},
{"learn":[0.03638737514],"iteration":231,"passed_time":0.2872979052,"remaining_time":0.9510551345},
{"learn":[0.03637189988],"iteration":232,"passed_time":0.2899818224,"remaining_time":0.9545753554},
{"learn":[0.03633138094],"iteration":233,"passed_time":0.2920282139,"remaining_time":0.9559556063},
{"learn":[0.03628657534],"iteration":234,"passed_time":0.2931921057,"remaining_time":0.954433876},
{"learn":[0.03621463016],"iteration":235,"passed_time":0.2941474771,"remaining_time":0.9522401376},
{"learn":[0.03616806607],"iteration":236,"passed_time":0.2950192278,"remaining_time":0.9497876406},
{"learn":[0.03609923127],"iteration":237,"passed_time":0.2958284948,"remaining_time":0.9471483741},
{"learn":[0.03598381993],"iteration":238,"passed_time":0.296558659,"remaining_time":0.9442725501},
{"learn":[0.03588288592],"iteration":239,"passed_time":0.2972532651,"remaining_time":0.9413020062},
{"learn":[0.03578409309],"iteration":240,"passed_time":0.2981145436,"remaining_time":0.9388752638},
{"learn":[0.03570694629],"iteration":241,"passed_time":0.2989662098,"remaining_time":0.9364313512},
{"learn":[0.03564323418],"iteration":242,"passed_time":0.2998443639,"remaining_time":0.9340830595},
{"learn":[0.0355159784],"iteration":243,"passed_time":0.3011850314,"remaining_time":0.9331798514},
{"learn":[0.03539189634],"iteration":244,"passed_time":0.3021707219,"remaining_time":0.9311791633},
{"learn":[0.03533673208],"iteration":245,"passed_time":0.304456764,"remaining_time":0.9331723579},
{"learn":[0.0352683093],"iteration":246,"passed_time":0.306116636,"remaining_time":0.9332219713},
{"learn":[0.03520131188],"iteration":247,"passed_time":0.3070532617,"remaining_time":0.931064729},
{"learn":[0.03509948936],"iteration":248,"passed_time":0.3079246769,"remaining_time":0.9287206118},
{"learn":[0.03499068242],"iteration":249,"passed_time":0.3087530329,"remaining_time":0.9262590987},
{"learn":[0.03494816782],"iteration":250,"passed_time":0.30958238,"remaining_time":0.9238135563},
{"learn":[0.03486995327],"iteration":251,"passed_time":0.3106770157,"remaining_time":0.9221682848},
{"learn":[0.03478232453],"iteration":252,"passed_time":0.3114272067,"remaining_time":0.9195103692},
{"learn":[0.03473782628],"iteration":253,"passed_time":0.3121232862,"remaining_time":0.9167085493},
{"learn":[0.03467306714],"iteration":254,"passed_time":0.3128081367,"remaining_time":0.9138904387},
{"learn":[0.03464326001],"iteration":255,"passed_time":0.3135103851,"remaining_time":0.9111395568},
{"learn":[0.03460161342],"iteration":256,"passed_time":0.314255165,"remaining_time":0.9085275782},
{"learn":[0.03450175605],"iteration":257,"passed_time":0.3150859832,"remaining_time":0.9061775177},
{"learn":[0.03445440096],"iteration":258,"passed_time":0.317325425,"remaining_time":0.9078692662},
{"learn":[0.03441035825],"iteration":259,"passed_time":0.3193637909,"remaining_time":0.9089584818},
{"learn":[0.0342993162],"iteration":260,"passed_time":0.3211719173,"remaining_time":0.9093718272},
{"learn":[0.03427089608],"iteration":261,"passed_time":0.322258303,"remaining_time":0.9077352199},
{"learn":[0.03416614386],"iteration":262,"passed_time":0.3233589998,"remaining_time":0.9061429007},
{"learn":[0.03408590213],"iteration":263,"passed_time":0.3242251128,"remaining_time":0.9039003144},
{"learn":[0.03398935765],"iteration":264,"passed_time":0.3250489299,"remaining_time":0.9015508055},
{"learn":[0.03391627215],"iteration":265,"passed_time":0.3258279566,"remaining_time":0.8990891736},
{"learn":[0.03382956209],"iteration":266,"passed_time":0.3265687931,"remaining_time":0.8965353009},
{"learn":[0.03379586383],"iteration":267,"passed_time":0.3272731404,"remaining_time":0.893895294},
{"learn":[0.03371284228],"iteration":268,"passed_time":0.3280144591,"remaining_time":0.8913701473},
{"learn":[0.03365393569],"iteration":269,"passed_time":0.3287718413,"remaining_time":0.888901645},
{"learn":[0.03363137313],"iteration":270,"passed_time":0.3296908746,"remaining_time":0.8868806184},
{"learn":[0.03356511985],"iteration":271,"passed_time":0.3308223339,"remaining_time":0.8854362467},
{"learn":[0.03353588168],"iteration":272,"passed_time":0.3326541128,"remaining_time":0.8858591208},
{"learn":[0.03348156446],"iteration":273,"passed_time":0.334640726,"remaining_time":0.8866757924},
{"learn":[0.03341141986],"iteration":274,"passed_time":0.3355545693,"remaining_time":0.8846438646},
{"learn":[0.03337098206],"iteration":275,"passed_time":0.336376092,"remaining_time":0.8823778644},
{"learn":[0.03330427398],"iteration":276,"passed_time":0.3373786414,"remaining_time":0.8805947934},
{"learn":[0.03323283503],"iteration":277,"passed_time":0.3384188456,"remaining_time":0.8789151315},
{"learn":[0.03320169773],"iteration":278,"passed_time":0.3396309122,"remaining_time":0.8776841853},
{"learn":[0.03313857853],"iteration":279,"passed_time":0.3410461113,"remaining_time":0.8769757149},
{"learn":[0.03305081375],"iteration":280,"passed_time":0.342105889,"remaining_time":0.8753527908},
{"learn":[0.03294447011],"iteration":281,"passed_time":0.3431568566,"remaining_time":0.8737114293},
{"learn":[0.03288870931],"iteration":282,"passed_time":0.3442299555,"remaining_time":0.8721303114},
{"learn":[0.03283194261],"iteration":283,"passed_time":0.3453517737,"remaining_time":0.8706755984},
{"learn":[0.03279301277],"iteration":284,"passed_time":0.347164819,"remaining_time":0.870957353},
{"learn":[0.03272150213],"iteration":285,"passed_time":0.3489868211,"remaining_time":0.8712468191},
{"learn":[0.0326597874],"iteration":286,"passed_time":0.3499533981,"remaining_time":0.8693964211},
{"learn":[0.03260090141],"iteration":287,"passed_time":0.3507242404,"remaining_time":0.8670682609},
{"learn":[0.03251442328],"iteration":288,"passed_time":0.3515618031,"remaining_time":0.8649150242},
{"learn":[0.03242476658],"iteration":289,"passed_time":0.3524799942,"remaining_time":0.8629682617},
{"learn":[0.03236493066],"iteration":290,"passed_time":0.3532986957,"remaining_time":0.8607861692},
{"learn":[0.03227973596],"iteration":291,"passed_time":0.3542024667,"remaining_time":0.8588196795},
{"learn":[0.03224064553],"iteration":292,"passed_time":0.355008567,"remaining_time":0.8566247674},
{"learn":[0.03218920421],"iteration":293,"passed_time":0.35572791,"remaining_time":0.8542309675},
{"learn":[0.03215289359],"iteration":294,"passed_time":0.3564459141,"remaining_time":0.85184532},
{"learn":[0.03211522937],"iteration":295,"passed_time":0.357152457,"remaining_time":0.8494436814},
{"learn":[0.03209629449],"iteration":296,"passed_time":0.3578720522,"remaining_time":0.8470843524},
{"learn":[0.03201164623],"iteration":297,"passed_time":0.3587598308,"remaining_time":0.8451322189},
{"learn":[0.03198834875],"iteration":298,"passed_time":0.3597321701,"remaining_time":0.8433854556},
{"learn":[0.03192870691],"iteration":299,"passed_time":0.3613984644,"remaining_time":0.8432630836},
{"learn":[0.03186485172],"iteration":300,"passed_time":0.3622888131,"remaining_time":0.8413285061},
{"learn":[0.03185094717],"iteration":301,"passed_time":0.3630803221,"remaining_time":0.8391724002},
{"learn":[0.03182124935],"iteration":302,"passed_time":0.3642436961,"remaining_time":0.8378807135},
{"learn":[0.03180376594],"iteration":303,"passed_time":0.365121058,"remaining_time":0.8359350539},
{"learn":[0.03176653803],"iteration":304,"passed_time":0.3659087193,"remaining_time":0.8337919997},
{"learn":[0.03173499521],"iteration":305,"passed_time":0.3666934139,"remaining_time":0.8316510759},
{"learn":[0.03170073246],"iteration":306,"passed_time":0.367448986,"remaining_time":0.8294532485},
{"learn":[0.03167255017],"iteration":307,"passed_time":0.3681839758,"remaining_time":0.827218543},
{"learn":[0.03160975834],"iteration":308,"passed_time":0.3692853638,"remaining_time":0.8258129008},
{"learn":[0.03152571979],"iteration":309,"passed_time":0.3701506723,"remaining_time":0.8238837544},
{"learn":[0.03150792858],"iteration":310,"passed_time":0.37106237,"remaining_time":0.8220642216},
{"learn":[0.03148827252],"iteration":311,"passed_time":0.371858408,"remaining_time":0.8199954637},
{"learn":[0.03140214043],"iteration":312,"passed_time":0.3726173146,"remaining_time":0.817853339},
{"learn":[0.03137961484],"iteration":313,"passed_time":0.3733774656,"remaining_time":0.8157227434},
{"learn":[0.03135052797],"iteration":314,"passed_time":0.3747836647,"remaining_time":0.8150057471},
{"learn":[0.0313147755],"iteration":315,"passed_time":0.3777652119,"remaining_time":0.8176943194},
{"learn":[0.03129667306],"iteration":316,"passed_time":0.3795931818,"remaining_time":0.8178616503},
{"learn":[0.03124208939],"iteration":317,"passed_time":0.3807755126,"remaining_time":0.8166317597},
{"learn":[0.03122554387],"iteration":318,"passed_time":0.38180415,"remaining_time":0.8150740632},
{"learn":[0.03115193267],"iteration":319,"passed_time":0.3829562862,"remaining_time":0.8137821081},
{"learn":[0.03108319483],"iteration":320,"passed_time":0.3837724598,"remaining_time":0.8117803746},
{"learn":[0.03100655322],"iteration":321,"passed_time":0.3845805513,"remaining_time":0.8097689868},
{"learn":[0.03097512715],"iteration":322,"passed_time":0.3853583902,"remaining_time":0.8077016414},
{"learn":[0.0309592706],"iteration":323,"passed_time":0.3860784099,"remaining_time":0.8055216206},
{"learn":[0.03093498781],"iteration":324,"passed_time":0.3867696416,"remaining_time":0.803290794},
{"learn":[0.03090070848],"iteration":325,"passed_time":0.3874319197,"remaining_time":0.8010095518},
{"learn":[0.03086359965],"iteration":326,"passed_time":0.388408709,"remaining_time":0.7993855081},
{"learn":[0.03081202731],"iteration":327,"passed_time":0.3893790116,"remaining_time":0.7977521213},
{"learn":[0.03076360716],"iteration":328,"passed_time":0.3925401612,"remaining_time":0.8005910278},
{"learn":[0.03072428995],"iteration":329,"passed_time":0.3946233307,"remaining_time":0.8012049441},
{"learn":[0.03064893699],"iteration":330,"passed_time":0.3961001847,"remaining_time":0.8005771105},
{"learn":[0.03055723979],"iteration":331,"passed_time":0.3972435886,"remaining_time":0.7992732445},
{"learn":[0.03048782061],"iteration":332,"passed_time":0.3984182804,"remaining_time":0.7980330121},
{"learn":[0.0304502829],"iteration":333,"passed_time":0.3992920112,"remaining_time":0.7961930523},
{"learn":[0.03040138241],"iteration":334,"passed_time":0.4001053182,"remaining_time":0.7942389152},
{"learn":[0.03038757078],"iteration":335,"passed_time":0.4008882461,"remaining_time":0.792231534},
{"learn":[0.03034115641],"iteration":336,"passed_time":0.4015974112,"remaining_time":0.7900863016},
{"learn":[0.03032354839],"iteration":337,"passed_time":0.4023952381,"remaining_time":0.7881232179},
{"learn":[0.03028404611],"iteration":338,"passed_time":0.4035893479,"remaining_time":0.7869397019},
{"learn":[0.03021886812],"iteration":339,"passed_time":0.4045495537,"remaining_time":0.7853020749},
{"learn":[0.03020297891],"iteration":340,"passed_time":0.408267494,"remaining_time":0.7889978843},
{"learn":[0.03014550636],"iteration":341,"passed_time":0.4092343377,"remaining_time":0.787357293},
{"learn":[0.03011035033],"iteration":342,"passed_time":0.4100537203,"remaining_time":0.7854381756},
{"learn":[0.0300931979],"iteration":343,"passed_time":0.4108770974,"remaining_time":0.7835330694},
{"learn":[0.03005816749],"iteration":344,"passed_time":0.4115863092,"remaining_time":0.7814174855},
{"learn":[0.02999538939],"iteration":345,"passed_time":0.4123067588,"remaining_time":0.7793312725},
{"learn":[0.02997077942],"iteration":346,"passed_time":0.4130155206,"remaining_time":0.7772309365},
{"learn":[0.02995604685],"iteration":347,"passed_time":0.4137192413,"remaining_time":0.7751291532},
{"learn":[0.0298905656],"iteration":348,"passed_time":0.4144337409,"remaining_time":0.7730554881},
{"learn":[0.02987630596],"iteration":349,"passed_time":0.4151507717,"remaining_time":0.7709942902},
{"learn":[0.02986238479],"iteration":350,"passed_time":0.4158603035,"remaining_time":0.7689268859},
{"learn":[0.02979641746],"iteration":351,"passed_time":0.4167071441,"remaining_time":0.7671199697},
{"learn":[0.02975796648],"iteration":352,"passed_time":0.4181271566,"remaining_time":0.7663690377},
{"learn":[0.02968917167],"iteration":353,"passed_time":0.422712082,"remaining_time":0.7713898446},
{"learn":[0.02965865102],"iteration":354,"passed_time":0.4242699144,"remaining_time":0.7708566051},
{"learn":[0.0295966314],"iteration":355,"passed_time":0.4254825677,"remaining_time":0.7696931842},
{"learn":[0.02956258923],"iteration":356,"passed_time":0.426509054,"remaining_time":0.7681941785},
{"learn":[0.02952859109],"iteration":357,"passed_time":0.4273128754,"remaining_time":0.7662985083},
{"learn":[0.02947468997],"iteration":358,"passed_time":0.4281923917,"remaining_time":0.7645440755},
{"learn":[0.02940323505],"iteration":359,"passed_time":0.4290351156,"remaining_time":0.7627290944},
{"learn":[0.02938394182],"iteration":360,"passed_time":0.4298318114,"remaining_time":0.7608380263},
{"learn":[0.02931009333],"iteration":361,"passed_time":0.4305945469,"remaining_time":0.7588931517},
{"learn":[0.02927773593],"iteration":362,"passed_time":0.4313177322,"remaining_time":0.7568853867},
{"learn":[0.02924735648],"iteration":363,"passed_time":0.4321474771,"remaining_time":0.7550708665},
{"learn":[0.0291901106],"iteration":364,"passed_time":0.4331911102,"remaining_time":0.7536338492},
{"learn":[0.02911811269],"iteration":365,"passed_time":0.4345568923,"remaining_time":0.7527570211},
{"learn":[0.02909858325],"iteration":366,"passed_time":0.4361350537,"remaining_time":0.7522438393},
{"learn":[0.02902675297],"iteration":367,"passed_time":0.437370016,"remaining_time":0.7511354623},
{"learn":[0.02898950928],"iteration":368,"passed_time":0.4382431779,"remaining_time":0.7494077107},
{"learn":[0.02894600542],"iteration":369,"passed_time":0.4390961819,"remaining_time":0.7476502556},
{"learn":[0.02888123675],"iteration":370,"passed_time":0.4399927072,"remaining_time":0.7459714632},
{"learn":[0.02884569983],"iteration":371,"passed_time":0.440862828,"remaining_time":0.744252301},
{"learn":[0.02877105227],"iteration":372,"passed_time":0.4417234709,"remaining_time":0.7425217594},
{"learn":[0.02868969384],"iteration":373,"passed_time":0.4425120266,"remaining_time":0.7406752103},
{"learn":[0.02866458302],"iteration":374,"passed_time":0.4435121194,"remaining_time":0.7391868657},
{"learn":[0.02857617239],"iteration":375,"passed_time":0.4444892387,"remaining_time":0.7376629919},
{"learn":[0.02851222802],"iteration":376,"passed_time":0.4456898807,"remaining_time":0.7365113944},
{"learn":[0.02844982715],"iteration":377,"passed_time":0.4478121483,"remaining_time":0.7368760748},
{"learn":[0.02840591684],"iteration":378,"passed_time":0.4500287877,"remaining_time":0.7373822617},
{"learn":[0.02838695754],"iteration":379,"passed_time":0.451741289,"remaining_time":0.7370515769},
{"learn":[0.02836523433],"iteration":380,"passed_time":0.4526423334,"remaining_time":0.735395287},
{"learn":[0.02833095365],"iteration":381,"passed_time":0.4535592544,"remaining_time":0.7337686368},
{"learn":[0.02831197061],"iteration":382,"passed_time":0.4544058084,"remaining_time":0.7320323336},
{"learn":[0.02826009402],"iteration":383,"passed_time":0.4552239043,"remaining_time":0.7302550131},
{"learn":[0.02821549653],"iteration":384,"passed_time":0.4560697993,"remaining_time":0.728527082},
{"learn":[0.02815812064],"iteration":385,"passed_time":0.4568584639,"remaining_time":0.7267126861},
{"learn":[0.02813039319],"iteration":386,"passed_time":0.4575810069,"remaining_time":0.7247988559},
{"learn":[0.02807285804],"iteration":387,"passed_time":0.4583004999,"remaining_time":0.7228863555},
{"learn":[0.02804322273],"iteration":388,"passed_time":0.4590276774,"remaining_time":0.7209920588},
{"learn":[0.02802006193],"iteration":389,"passed_time":0.4597467226,"remaining_time":0.7190910277},
{"learn":[0.02800938778],"iteration":390,"passed_time":0.4606292301,"remaining_time":0.7174506423},
{"learn":[0.02795009683],"iteration":391,"passed_time":0.4617123935,"remaining_time":0.7161253451},
{"learn":[0.02793510219],"iteration":392,"passed_time":0.4637152325,"remaining_time":0.7162217458},
{"learn":[0.02790982146],"iteration":393,"passed_time":0.4658491624,"remaining_time":0.7165091178},
{"learn":[0.02787993779],"iteration":394,"passed_time":0.4666642361,"remaining_time":0.7147642097},
{"learn":[0.02786868337],"iteration":395,"passed_time":0.4675383002,"remaining_time":0.713113973},
{"learn":[0.02782643144],"iteration":396,"passed_time":0.4684075254,"remaining_time":0.7114602967},
{"learn":[0.02780265483],"iteration":397,"passed_time":0.469564156,"remaining_time":0.7102452811},
{"learn":[0.02776489213],"iteration":398,"passed_time":0.4703969609,"remaining_time":0.7085427907},
{"learn":[0.02772041417],"iteration":399,"passed_time":0.471183851,"remaining_time":0.7067757766},
{"learn":[0.02769890018],"iteration":400,"passed_time":0.4719712567,"remaining_time":0.7050144209},
{"learn":[0.02761482068],"iteration":401,"passed_time":0.4727628825,"remaining_time":0.7032641884},
{"learn":[0.02758140522],"iteration":402,"passed_time":0.473622682,"remaining_time":0.7016197052},
{"learn":[0.02754899458],"iteration":403,"passed_time":0.4744368568,"remaining_time":0.6999117987},
{"learn":[0.02753884693],"iteration":404,"passed_time":0.4753223399,"remaining_time":0.6983130673},
{"learn":[0.02752001414],"iteration":405,"passed_time":0.4774008439,"remaining_time":0.6984633036},
{"learn":[0.02750178541],"iteration":406,"passed_time":0.4807063589,"remaining_time":0.7003903461},
{"learn":[0.02744707785],"iteration":407,"passed_time":0.4823043883,"remaining_time":0.6998142105},
{"learn":[0.02738770069],"iteration":408,"passed_time":0.4834785601,"remaining_time":0.6986206089},
{"learn":[0.02734551746],"iteration":409,"passed_time":0.4845971038,"remaining_time":0.6973470518},
{"learn":[0.02732348242],"iteration":410,"passed_time":0.4855238094,"remaining_time":0.6957993278},
{"learn":[0.02727361127],"iteration":411,"passed_time":0.4864288793,"remaining_time":0.6942237403},
{"learn":[0.02721692995],"iteration":412,"passed_time":0.4872460108,"remaining_time":0.6925264124},
{"learn":[0.02718460897],"iteration":413,"passed_time":0.4880490121,"remaining_time":0.690813336},
{"learn":[0.02713893907],"iteration":414,"passed_time":0.4888837304,"remaining_time":0.6891493549},
{"learn":[0.02710556196],"iteration":415,"passed_time":0.4902183723,"remaining_time":0.6881911765},
{"learn":[0.02705634388],"iteration":416,"passed_time":0.4912070272,"remaining_time":0.6867474745},
{"learn":[0.02703088145],"iteration":417,"passed_time":0.4935845011,"remaining_time":0.6872396643},
{"learn":[0.02702175254],"iteration":418,"passed_time":0.4950910087,"remaining_time":0.6865104441},
{"learn":[0.02695948134],"iteration":419,"passed_time":0.4962109968,"remaining_time":0.6852437575},
{"learn":[0.0269376461],"iteration":420,"passed_time":0.4973593352,"remaining_time":0.6840167579},
{"learn":[0.02689341919],"iteration":421,"passed_time":0.4988548904,"remaining_time":0.683265703},
{"learn":[0.02684166984],"iteration":422,"passed_time":0.5001614221,"remaining_time":0.6822532874},
{"learn":[0.02677108629],"iteration":423,"passed_time":0.5013450529,"remaining_time":0.6810725247},
{"learn":[0.02676120746],"iteration":424,"passed_time":0.502243625,"remaining_time":0.6795060809},
{"learn":[0.02670969],"iteration":425,"passed_time":0.5030751566,"remaining_time":0.677852441},
{"learn":[0.02665384169],"iteration":426,"passed_time":0.5039947266,"remaining_time":0.6763207923},
{"learn":[0.02661724798],"iteration":427,"passed_time":0.5052060554,"remaining_time":0.6751819245},
{"learn":[0.02657025354],"iteration":428,"passed_time":0.5062713209,"remaining_time":0.6738483082},
{"learn":[0.02652630923],"iteration":429,"passed_time":0.5082333117,"remaining_time":0.6737046225},
{"learn":[0.02651716492],"iteration":430,"passed_time":0.5096870834,"remaining_time":0.6728815556},
{"learn":[0.02648663257],"iteration":431,"passed_time":0.5105061715,"remaining_time":0.6712210774},
{"learn":[0.02642823793],"iteration":432,"passed_time":0.5113321597,"remaining_time":0.669573521},
{"learn":[0.0264098707],"iteration":433,"passed_time":0.5121152121,"remaining_time":0.6678737559},
{"learn":[0.02637363633],"iteration":434,"passed_time":0.5129657571,"remaining_time":0.6662658685},
{"learn":[0.0263230638],"iteration":435,"passed_time":0.5136869735,"remaining_time":0.6644941584},
{"learn":[0.02628098825],"iteration":436,"passed_time":0.5144083909,"remaining_time":0.6627275151},
{"learn":[0.02626827858],"iteration":437,"passed_time":0.5151181472,"remaining_time":0.660950682},
{"learn":[0.02620781948],"iteration":438,"passed_time":0.5158214534,"remaining_time":0.6591704678},
{"learn":[0.02618649957],"iteration":439,"passed_time":0.5165276396,"remaining_time":0.6573988141},
{"learn":[0.02616896765],"iteration":440,"passed_time":0.5172277891,"remaining_time":0.6556243404},
{"learn":[0.02614165784],"iteration":441,"passed_time":0.5180716997,"remaining_time":0.6540362182},
{"learn":[0.02611653709],"iteration":442,"passed_time":0.519352419,"remaining_time":0.6530006713},
{"learn":[0.02606761024],"iteration":443,"passed_time":0.5206675074,"remaining_time":0.6520070588},
{"learn":[0.02603968526],"iteration":444,"passed_time":0.521765102,"remaining_time":0.6507407452},
{"learn":[0.02600898407],"iteration":445,"passed_time":0.522642135,"remaining_time":0.6492012171},
{"learn":[0.025965603],"iteration":446,"passed_time":0.5236707769,"remaining_time":0.647852214},
{"learn":[0.02595426551],"iteration":447,"passed_time":0.5245164331,"remaining_time":0.6462791765},
{"learn":[0.02592880474],"iteration":448,"passed_time":0.5253318779,"remaining_time":0.6446723045},
{"learn":[0.02585727226],"iteration":449,"passed_time":0.5260981467,"remaining_time":0.643008846},
{"learn":[0.0258436683],"iteration":450,"passed_time":0.5268347399,"remaining_time":0.6413132421},
{"learn":[0.02582223847],"iteration":451,"passed_time":0.5275137159,"remaining_time":0.6395520272},
{"learn":[0.02577882458],"iteration":452,"passed_time":0.5281921364,"remaining_time":0.6377949196},
{"learn":[0.02576157075],"iteration":453,"passed_time":0.5288931581,"remaining_time":0.6360697452},
{"learn":[0.02575925877],"iteration":454,"passed_time":0.5295866343,"remaining_time":0.6343400344},
{"learn":[0.02573771631],"iteration":455,"passed_time":0.5302797826,"remaining_time":0.6326144775},
{"learn":[0.02571420907],"iteration":456,"passed_time":0.5309474063,"remaining_time":0.6308631108},
{"learn":[0.02568727032],"iteration":457,"passed_time":0.531762,"remaining_time":0.6292904018},
{"learn":[0.02566595632],"iteration":458,"passed_time":0.5324517106,"remaining_time":0.6275738027},
{"learn":[0.02565398341],"iteration":459,"passed_time":0.5332502597,"remaining_time":0.6259894353},
{"learn":[0.02564923446],"iteration":460,"passed_time":0.5348112021,"remaining_time":0.6252998654},
{"learn":[0.02563341834],"iteration":461,"passed_time":0.5387744819,"remaining_time":0.6274040504},
{"learn":[0.0256064013],"iteration":462,"passed_time":0.5400031853,"remaining_time":0.6263103898},
{"learn":[0.02556907171],"iteration":463,"passed_time":0.541339395,"remaining_time":0.6253403356},
{"learn":[0.02553716334],"iteration":464,"passed_time":0.5423337988,"remaining_time":0.623975446},
{"learn":[0.02552422065],"iteration":465,"passed_time":0.5435041095,"remaining_time":0.6228137221},
{"learn":[0.02549080457],"iteration":466,"passed_time":0.5443477523,"remaining_time":0.6212791263},
{"learn":[0.0254885247],"iteration":467,"passed_time":0.5451284147,"remaining_time":0.6196758902},
{"learn":[0.02547811319],"iteration":468,"passed_time":0.5458798623,"remaining_time":0.6180430851},
{"learn":[0.02543048163],"iteration":469,"passed_time":0.5467641498,"remaining_time":0.6165638285},
{"learn":[0.02541543173],"iteration":470,"passed_time":0.5479646352,"remaining_time":0.6154422336},
{"learn":[0.02536560079],"iteration":471,"passed_time":0.5506357046,"remaining_time":0.6159653644},
{"learn":[0.0253233061],"iteration":472,"passed_time":0.5538875215,"remaining_time":0.6171220376},
{"learn":[0.02530353165],"iteration":473,"passed_time":0.5568541441,"remaining_time":0.6179436282},
{"learn":[0.02529547653],"iteration":474,"passed_time":0.5581704214,"remaining_time":0.6169252026},
{"learn":[0.02521129314],"iteration":475,"passed_time":0.5600713085,"remaining_time":0.6165490875},
{"learn":[0.02516040027],"iteration":476,"passed_time":0.5625291074,"remaining_time":0.6167771974},
{"learn":[0.02510475597],"iteration":477,"passed_time":0.5639449332,"remaining_time":0.6158561823},
{"learn":[0.02505299897],"iteration":478,"passed_time":0.5649412049,"remaining_time":0.6144767594},
{"learn":[0.02500712343],"iteration":479,"passed_time":0.5657291006,"remaining_time":0.6128731923},
{"learn":[0.02499211993],"iteration":480,"passed_time":0.566630346,"remaining_time":0.6113953214},
{"learn":[0.02494042759],"iteration":481,"passed_time":0.5675265914,"remaining_time":0.6099144696},
{"learn":[0.02489429423],"iteration":482,"passed_time":0.5684136134,"remaining_time":0.6084261659},
{"learn":[0.02484670456],"iteration":483,"passed_time":0.5692577251,"remaining_time":0.6068945994},
{"learn":[0.02478855163],"iteration":484,"passed_time":0.5701007034,"remaining_time":0.6053646644},
{"learn":[0.02477436312],"iteration":485,"passed_time":0.5710348968,"remaining_time":0.6039340267},
{"learn":[0.02475925087],"iteration":486,"passed_time":0.5720585065,"remaining_time":0.6025996177},
{"learn":[0.02473401092],"iteration":487,"passed_time":0.5734437532,"remaining_time":0.601645905},
{"learn":[0.02471637177],"iteration":488,"passed_time":0.5764490605,"remaining_time":0.6023833741},
{"learn":[0.02469931532],"iteration":489,"passed_time":0.5784684596,"remaining_time":0.6020794171},
{"learn":[0.0246392904],"iteration":490,"passed_time":0.5796689472,"remaining_time":0.6009195399},
{"learn":[0.02463479202],"iteration":491,"passed_time":0.5805080077,"remaining_time":0.5993863169},
{"learn":[0.02460334191],"iteration":492,"passed_time":0.5813139246,"remaining_time":0.5978218251},
{"learn":[0.0245770815],"iteration":493,"passed_time":0.5821390462,"remaining_time":0.5962800756},
{"learn":[0.02454189208],"iteration":494,"passed_time":0.5829551643,"remaining_time":0.5947320363},
{"learn":[0.02451908287],"iteration":495,"passed_time":0.5837428556,"remaining_time":0.5931580629},
{"learn":[0.02450783174],"iteration":496,"passed_time":0.5844593119,"remaining_time":0.5915151587},
{"learn":[0.02447694458],"iteration":497,"passed_time":0.585175496,"remaining_time":0.5898757007},
{"learn":[0.02443312266],"iteration":498,"passed_time":0.5858708721,"remaining_time":0.588219052},
{"learn":[0.02439415837],"iteration":499,"passed_time":0.5866034096,"remaining_time":0.5866034096},
{"learn":[0.02434957282],"iteration":500,"passed_time":0.5873106359,"remaining_time":0.5849660824},
{"learn":[0.02429975546],"iteration":501,"passed_time":0.5881064683,"remaining_time":0.583420361},
{"learn":[0.02427643651],"iteration":502,"passed_time":0.5893690819,"remaining_time":0.5823388344},
{"learn":[0.02423306564],"iteration":503,"passed_time":0.5913753276,"remaining_time":0.5819884176},
{"learn":[0.02419656219],"iteration":504,"passed_time":0.5928985875,"remaining_time":0.5811580214},
{"learn":[0.02413521233],"iteration":505,"passed_time":0.5938719156,"remaining_time":0.5797879967},
{"learn":[0.02408981684],"iteration":506,"passed_time":0.5947052417,"remaining_time":0.5782834007},
{"learn":[0.02406308021],"iteration":507,"passed_time":0.595528631,"remaining_time":0.5767718237},
{"learn":[0.02402375261],"iteration":508,"passed_time":0.5963138378,"remaining_time":0.5752261186},
{"learn":[0.02401253361],"iteration":509,"passed_time":0.5970348675,"remaining_time":0.5736217354},
{"learn":[0.02397662094],"iteration":510,"passed_time":0.5981456755,"remaining_time":0.5723938069},
{"learn":[0.02395641044],"iteration":511,"passed_time":0.5989565025,"remaining_time":0.5708804164},
{"learn":[0.02392908843],"iteration":512,"passed_time":0.5998257621,"remaining_time":0.5694252362},
{"learn":[0.02389693626],"iteration":513,"passed_time":0.6006364891,"remaining_time":0.5679169916},
{"learn":[0.02384536177],"iteration":514,"passed_time":0.6013503676,"remaining_time":0.5663202491},
{"learn":[0.02381478759],"iteration":515,"passed_time":0.6020445404,"remaining_time":0.5647084449},
{"learn":[0.0237777175],"iteration":516,"passed_time":0.6027350465,"remaining_time":0.5630967649},
{"learn":[0.02373539967],"iteration":517,"passed_time":0.6039425686,"remaining_time":0.561969726},
{"learn":[0.02369877687],"iteration":518,"passed_time":0.6068177261,"remaining_time":0.5623879119},
{"learn":[0.02365859642],"iteration":519,"passed_time":0.6085393375,"remaining_time":0.5617286192},
{"learn":[0.02361804408],"iteration":520,"passed_time":0.6097996488,"remaining_time":0.5606411359},
{"learn":[0.02360381433],"iteration":521,"passed_time":0.6110707658,"remaining_time":0.5595628852},
{"learn":[0.02358897516],"iteration":522,"passed_time":0.6122362609,"remaining_time":0.5583875649},
{"learn":[0.02355051997],"iteration":523,"passed_time":0.6131107839,"remaining_time":0.556947964},
{"learn":[0.02351881043],"iteration":524,"passed_time":0.6139523589,"remaining_time":0.5554807057},
{"learn":[0.02349059458],"iteration":525,"passed_time":0.6147936884,"remaining_time":0.5540156051},
{"learn":[0.0234252187],"iteration":526,"passed_time":0.6155987653,"remaining_time":0.5525203339},
{"learn":[0.02338826032],"iteration":527,"passed_time":0.6163193483,"remaining_time":0.5509521447},
{"learn":[0.023342003],"iteration":528,"passed_time":0.6170186511,"remaining_time":0.549368213},
{"learn":[0.02332712077],"iteration":529,"passed_time":0.6181363192,"remaining_time":0.5481586227},
{"learn":[0.0232705333],"iteration":530,"passed_time":0.6190662871,"remaining_time":0.5467835944},
{"learn":[0.02324916016],"iteration":531,"passed_time":0.6211669712,"remaining_time":0.5464401175},
{"learn":[0.02323500864],"iteration":532,"passed_time":0.6228361155,"remaining_time":0.5457119436},
{"learn":[0.02320967604],"iteration":533,"passed_time":0.623823816,"remaining_time":0.5443855773},
{"learn":[0.02315925865],"iteration":534,"passed_time":0.6248313522,"remaining_time":0.5430777173},
{"learn":[0.02313829275],"iteration":535,"passed_time":0.6261804031,"remaining_time":0.5420666176},
{"learn":[0.02311717005],"iteration":536,"passed_time":0.6274943348,"remaining_time":0.5410239796},
{"learn":[0.02307206113],"iteration":537,"passed_time":0.6286692511,"remaining_time":0.5398609554},
{"learn":[0.02302586317],"iteration":538,"passed_time":0.6298130216,"remaining_time":0.5386712486},
{"learn":[0.02300602819],"iteration":539,"passed_time":0.6306834946,"remaining_time":0.5372489028},
{"learn":[0.02297529536],"iteration":540,"passed_time":0.6315161451,"remaining_time":0.5357965076},
{"learn":[0.02294227961],"iteration":541,"passed_time":0.632978879,"remaining_time":0.5348788314},
{"learn":[0.02293892238],"iteration":542,"passed_time":0.6345941941,"remaining_time":0.534087563},
{"learn":[0.02291014867],"iteration":543,"passed_time":0.6364219973,"remaining_time":0.5334713801},
{"learn":[0.02287293523],"iteration":544,"passed_time":0.6373853454,"remaining_time":0.5321290498},
{"learn":[0.02283971786],"iteration":545,"passed_time":0.638199198,"remaining_time":0.530663802},
{"learn":[0.02281862474],"iteration":546,"passed_time":0.6390302273,"remaining_time":0.5292151608},
{"learn":[0.02279144236],"iteration":547,"passed_time":0.6398439188,"remaining_time":0.5277544731},
{"learn":[0.02277516313],"iteration":548,"passed_time":0.6405758974,"remaining_time":0.5262290159},
{"learn":[0.02275948461],"iteration":549,"passed_time":0.6412832381,"remaining_time":0.5246862857},
{"learn":[0.02275121865],"iteration":550,"passed_time":0.6419942688,"remaining_time":0.5231495947},
{"learn":[0.02270952881],"iteration":551,"passed_time":0.6427082973,"remaining_time":0.5216183282},
{"learn":[0.02269002184],"iteration":552,"passed_time":0.643408339,"remaining_time":0.5200787117},
{"learn":[0.02266633758],"iteration":553,"passed_time":0.6441115697,"remaining_time":0.5185446933},
{"learn":[0.02264506777],"iteration":554,"passed_time":0.644830346,"remaining_time":0.5170261333},
{"learn":[0.0226077608],"iteration":555,"passed_time":0.6455591435,"remaining_time":0.5155184527},
{"learn":[0.0225889108],"iteration":556,"passed_time":0.6464639145,"remaining_time":0.5141535263},
{"learn":[0.02255182163],"iteration":557,"passed_time":0.649124046,"remaining_time":0.514180696},
{"learn":[0.02252055237],"iteration":558,"passed_time":0.6500852285,"remaining_time":0.5128579352},
{"learn":[0.02250485747],"iteration":559,"passed_time":0.6509499793,"remaining_time":0.511460698},
{"learn":[0.0224774879],"iteration":560,"passed_time":0.6518607647,"remaining_time":0.5101013827},
{"learn":[0.02247370751],"iteration":561,"passed_time":0.6526734906,"remaining_time":0.50866724},
{"learn":[0.02245115339],"iteration":562,"passed_time":0.6534578863,"remaining_time":0.507213315},
{"learn":[0.0224324965],"iteration":563,"passed_time":0.6542100195,"remaining_time":0.5057368236},
{"learn":[0.02241781688],"iteration":564,"passed_time":0.6549452149,"remaining_time":0.5042498557},
{"learn":[0.02240329315],"iteration":565,"passed_time":0.6556316421,"remaining_time":0.5027281496},
{"learn":[0.0223648319],"iteration":566,"passed_time":0.6563228249,"remaining_time":0.5012130214},
{"learn":[0.02234649002],"iteration":567,"passed_time":0.6570326278,"remaining_time":0.4997149563},
{"learn":[0.02234141736],"iteration":568,"passed_time":0.6577207728,"remaining_time":0.4982032567},
{"learn":[0.0223290257],"iteration":569,"passed_time":0.658399761,"remaining_time":0.496687539},
{"learn":[0.02230936532],"iteration":570,"passed_time":0.6590714392,"remaining_time":0.4951692599},
{"learn":[0.02226533219],"iteration":571,"passed_time":0.6599010219,"remaining_time":0.4937720933},
{"learn":[0.02223422445],"iteration":572,"passed_time":0.6608336364,"remaining_time":0.4924536872},
{"learn":[0.02222441766],"iteration":573,"passed_time":0.6621064745,"remaining_time":0.4913891257},
{"learn":[0.0222153295],"iteration":574,"passed_time":0.6663583054,"remaining_time":0.492525704},
{"learn":[0.02216675728],"iteration":575,"passed_time":0.6677729434,"remaining_time":0.4915550833},
{"learn":[0.02214273673],"iteration":576,"passed_time":0.6691140475,"remaining_time":0.4905290158},
{"learn":[0.02212077215],"iteration":577,"passed_time":0.6703034028,"remaining_time":0.4893910657},
{"learn":[0.02210641329],"iteration":578,"passed_time":0.6713743617,"remaining_time":0.4881668502},
{"learn":[0.02206844728],"iteration":579,"passed_time":0.6723713689,"remaining_time":0.486889612},
{"learn":[0.02205347951],"iteration":580,"passed_time":0.6735932433,"remaining_time":0.4857755059},
{"learn":[0.02201863235],"iteration":581,"passed_time":0.674458324,"remaining_time":0.4844047757},
{"learn":[0.02198388926],"iteration":582,"passed_time":0.6752918668,"remaining_time":0.483013222},
{"learn":[0.02195631557],"iteration":583,"passed_time":0.6763178009,"remaining_time":0.4817606253},
{"learn":[0.02194514422],"iteration":584,"passed_time":0.6787424829,"remaining_time":0.4815010776},
{"learn":[0.02190933953],"iteration":585,"passed_time":0.682092826,"remaining_time":0.4818881058},
{"learn":[0.02188809306],"iteration":586,"passed_time":0.683580039,"remaining_time":0.4809515436},
{"learn":[0.0218769633],"iteration":587,"passed_time":0.6848270103,"remaining_time":0.4798447759},
{"learn":[0.02184590187],"iteration":588,"passed_time":0.6860208001,"remaining_time":0.4787004224},
{"learn":[0.02181907782],"iteration":589,"passed_time":0.6868310348,"remaining_time":0.4772893632},
{"learn":[0.02179950644],"iteration":590,"passed_time":0.6876370862,"remaining_time":0.4758774421},
{"learn":[0.02177897388],"iteration":591,"passed_time":0.6884270108,"remaining_time":0.4744564534},
{"learn":[0.02176278121],"iteration":592,"passed_time":0.6892196343,"remaining_time":0.4730394455},
{"learn":[0.0217430278],"iteration":593,"passed_time":0.6900399803,"remaining_time":0.4716434882},
{"learn":[0.02170622146],"iteration":594,"passed_time":0.6909857338,"remaining_time":0.4703348272},
{"learn":[0.0216675007],"iteration":595,"passed_time":0.6920108012,"remaining_time":0.4690811471},
{"learn":[0.02165728311],"iteration":596,"passed_time":0.6943637561,"remaining_time":0.4687246126},
{"learn":[0.02162040548],"iteration":597,"passed_time":0.6958562702,"remaining_time":0.4677829776},
{"learn":[0.02156862004],"iteration":598,"passed_time":0.6967003808,"remaining_time":0.4664054302},
{"learn":[0.02153862715],"iteration":599,"passed_time":0.6975712982,"remaining_time":0.4650475321},
{"learn":[0.02151294601],"iteration":600,"passed_time":0.6984690203,"remaining_time":0.4637090501},
{"learn":[0.02147743741],"iteration":601,"passed_time":0.699425525,"remaining_time":0.4624108952},
{"learn":[0.02143159507],"iteration":602,"passed_time":0.7004810348,"remaining_time":0.4611790561},
{"learn":[0.0214272432],"iteration":603,"passed_time":0.7233519928,"remaining_time":0.4742506443},
{"learn":[0.02141231528],"iteration":604,"passed_time":0.7250575796,"remaining_time":0.4733847007},
{"learn":[0.02137819551],"iteration":605,"passed_time":0.7274639948,"remaining_time":0.4729716402},
{"learn":[0.02133369459],"iteration":606,"passed_time":0.729436568,"remaining_time":0.4722711223},
{"learn":[0.0213171834],"iteration":607,"passed_time":0.731425058,"remaining_time":0.4715766821},
{"learn":[0.02128271008],"iteration":608,"passed_time":0.7336284339,"remaining_time":0.4710159568},
{"learn":[0.02124648343],"iteration":609,"passed_time":0.7358288088,"remaining_time":0.4704479269},
{"learn":[0.02120774339],"iteration":610,"passed_time":0.7378164176,"remaining_time":0.469739094},
{"learn":[0.02118994779],"iteration":611,"passed_time":0.7397801618,"remaining_time":0.4690109523},
{"learn":[0.02114167888],"iteration":612,"passed_time":0.7416936646,"remaining_time":0.4682470607},
{"learn":[0.02113219841],"iteration":613,"passed_time":0.7439429764,"remaining_time":0.4676905357},
{"learn":[0.021078548],"iteration":614,"passed_time":0.7460143192,"remaining_time":0.4670170942},
{"learn":[0.02101611146],"iteration":615,"passed_time":0.748656735,"remaining_time":0.4666951076},
{"learn":[0.0210039825],"iteration":616,"passed_time":0.7509961531,"remaining_time":0.4661775148},
{"learn":[0.02100090995],"iteration":617,"passed_time":0.7534984446,"remaining_time":0.465754702},
{"learn":[0.02097746012],"iteration":618,"passed_time":0.7551597744,"remaining_time":0.464807551},
{"learn":[0.02095585791],"iteration":619,"passed_time":0.7566300395,"remaining_time":0.4637409919},
{"learn":[0.02092116164],"iteration":620,"passed_time":0.758260708,"remaining_time":0.4627710279},
{"learn":[0.02088792814],"iteration":621,"passed_time":0.7606283507,"remaining_time":0.4622468112},
{"learn":[0.02085703591],"iteration":622,"passed_time":0.7708122923,"remaining_time":0.4664466038},
{"learn":[0.02083116567],"iteration":623,"passed_time":0.7724358218,"remaining_time":0.4654420978},
{"learn":[0.02078270878],"iteration":624,"passed_time":0.7736139892,"remaining_time":0.4641683935},
{"learn":[0.02076135388],"iteration":625,"passed_time":0.7744739621,"remaining_time":0.4627048911},
{"learn":[0.02073833346],"iteration":626,"passed_time":0.7753319239,"remaining_time":0.4612421174},
{"learn":[0.02071464402],"iteration":627,"passed_time":0.7763535502,"remaining_time":0.4598782176},
{"learn":[0.02068953243],"iteration":628,"passed_time":0.7771760695,"remaining_time":0.4583979679},
{"learn":[0.02066610855],"iteration":629,"passed_time":0.7779853231,"remaining_time":0.4569120152},
{"learn":[0.0206458239],"iteration":630,"passed_time":0.7788241725,"remaining_time":0.4554455145},
{"learn":[0.02061927759],"iteration":631,"passed_time":0.7798028407,"remaining_time":0.4540624136},
{"learn":[0.02057656724],"iteration":632,"passed_time":0.7806229345,"remaining_time":0.4525886524},
{"learn":[0.02054429506],"iteration":633,"passed_time":0.7815020575,"remaining_time":0.45115103},
{"learn":[0.02053016267],"iteration":634,"passed_time":0.7827307986,"remaining_time":0.4499161283},
{"learn":[0.0205146228],"iteration":635,"passed_time":0.7838435778,"remaining_time":0.4486148779},
{"learn":[0.02049775133],"iteration":636,"passed_time":0.7849475358,"remaining_time":0.4473091923},
{"learn":[0.02044403531],"iteration":637,"passed_time":0.7858920515,"remaining_time":0.4459136719},
{"learn":[0.0204396428],"iteration":638,"passed_time":0.7869128534,"remaining_time":0.4445626605},
{"learn":[0.02041908334],"iteration":639,"passed_time":0.7880181114,"remaining_time":0.4432601877},
{"learn":[0.02040183197],"iteration":640,"passed_time":0.7894271994,"remaining_time":0.4421284939},
{"learn":[0.02038703404],"iteration":641,"passed_time":0.7904893804,"remaining_time":0.4408024894},
{"learn":[0.02035965042],"iteration":642,"passed_time":0.7931585909,"remaining_time":0.4403695442},
{"learn":[0.02035369337],"iteration":643,"passed_time":0.7949328559,"remaining_time":0.4394349328},
{"learn":[0.02033231587],"iteration":644,"passed_time":0.795970099,"remaining_time":0.43809207},
{"learn":[0.02029493958],"iteration":645,"passed_time":0.7983695497,"remaining_time":0.4374966263},
{"learn":[0.020247178],"iteration":646,"passed_time":0.8001283491,"remaining_time":0.4365460699},
{"learn":[0.02023732828],"iteration":647,"passed_time":0.8014699533,"remaining_time":0.4353663944},
{"learn":[0.02019713216],"iteration":648,"passed_time":0.8025460344,"remaining_time":0.4340426165},
{"learn":[0.02016571679],"iteration":649,"passed_time":0.8035210626,"remaining_time":0.4326651876},
{"learn":[0.02015240598],"iteration":650,"passed_time":0.8042713025,"remaining_time":0.4311684863},
{"learn":[0.02013120251],"iteration":651,"passed_time":0.804988911,"remaining_time":0.429656658},
{"learn":[0.02010911303],"iteration":652,"passed_time":0.8057086018,"remaining_time":0.4281483688},
{"learn":[0.02008626881],"iteration":653,"passed_time":0.8064315582,"remaining_time":0.4266442188},
{"learn":[0.02006581024],"iteration":654,"passed_time":0.8071663101,"remaining_time":0.4251486672},
{"learn":[0.02003754626],"iteration":655,"passed_time":0.8079286179,"remaining_time":0.423669885},
{"learn":[0.02002554121],"iteration":656,"passed_time":0.8087732396,"remaining_time":0.4222362575},
{"learn":[0.02000706926],"iteration":657,"passed_time":0.8095103616,"remaining_time":0.4207485466},
{"learn":[0.01996828142],"iteration":658,"passed_time":0.8101862765,"remaining_time":0.419231442},
{"learn":[0.0199649598],"iteration":659,"passed_time":0.8108613503,"remaining_time":0.4177164532},
{"learn":[0.01993780932],"iteration":660,"passed_time":0.8120120341,"remaining_time":0.4164479267},
{"learn":[0.01993660981],"iteration":661,"passed_time":0.8129788245,"remaining_time":0.4150858651},
{"learn":[0.01992086763],"iteration":662,"passed_time":0.8140809847,"remaining_time":0.4137938037},
{"learn":[0.01990009577],"iteration":663,"passed_time":0.8153523706,"remaining_time":0.4125879466},
{"learn":[0.01987812612],"iteration":664,"passed_time":0.8167671019,"remaining_time":0.411454104},
{"learn":[0.0198380169],"iteration":665,"passed_time":0.8182701406,"remaining_time":0.4103637041},
{"learn":[0.01980172463],"iteration":666,"passed_time":0.8192338976,"remaining_time":0.4090028304},
{"learn":[0.01978089152],"iteration":667,"passed_time":0.8204634176,"remaining_time":0.4077752315},
{"learn":[0.01974766968],"iteration":668,"passed_time":0.8212852625,"remaining_time":0.4063459221},
{"learn":[0.01970684256],"iteration":669,"passed_time":0.8219956998,"remaining_time":0.4048635536},
{"learn":[0.01968089255],"iteration":670,"passed_time":0.8229165398,"remaining_time":0.4034866492},
{"learn":[0.01965821509],"iteration":671,"passed_time":0.8236669208,"remaining_time":0.4020279018},
{"learn":[0.01961733683],"iteration":672,"passed_time":0.824434133,"remaining_time":0.4005794376},
{"learn":[0.01960097148],"iteration":673,"passed_time":0.8251498182,"remaining_time":0.3991080723},
{"learn":[0.01959043067],"iteration":674,"passed_time":0.8262568396,"remaining_time":0.3978273672},
{"learn":[0.01958759663],"iteration":675,"passed_time":0.8271260559,"remaining_time":0.3964331984},
{"learn":[0.01954424728],"iteration":676,"passed_time":0.8279910299,"remaining_time":0.3950385564},
{"learn":[0.01953147287],"iteration":677,"passed_time":0.8288357983,"remaining_time":0.3936358806},
{"learn":[0.01950243562],"iteration":678,"passed_time":0.829662792,"remaining_time":0.3922264451},
{"learn":[0.01948533292],"iteration":679,"passed_time":0.8306458436,"remaining_time":0.3908921617},
{"learn":[0.01947278413],"iteration":680,"passed_time":0.8313962846,"remaining_time":0.3894499483},
{"learn":[0.01943264383],"iteration":681,"passed_time":0.8321201987,"remaining_time":0.3879973947},
{"learn":[0.01942242366],"iteration":682,"passed_time":0.8327970225,"remaining_time":0.3865251188},
{"learn":[0.01937143267],"iteration":683,"passed_time":0.8336075184,"remaining_time":0.3851169237},
{"learn":[0.01934837132],"iteration":684,"passed_time":0.8346062434,"remaining_time":0.3837970316},
{"learn":[0.01931749789],"iteration":685,"passed_time":0.8354924665,"remaining_time":0.3824265809},
{"learn":[0.01930227794],"iteration":686,"passed_time":0.836324317,"remaining_time":0.3810327674},
{"learn":[0.01928404193],"iteration":687,"passed_time":0.8371552808,"remaining_time":0.3796401855},
{"learn":[0.01925019513],"iteration":688,"passed_time":0.8380048014,"remaining_time":0.3782576099},
{"learn":[0.01920701136],"iteration":689,"passed_time":0.8388084928,"remaining_time":0.3768559895},
{"learn":[0.01920582047],"iteration":690,"passed_time":0.8396520611,"remaining_time":0.3754739318},
{"learn":[0.01917637413],"iteration":691,"passed_time":0.8405121007,"remaining_time":0.3741007616},
{"learn":[0.01915121838],"iteration":692,"passed_time":0.8418451525,"remaining_time":0.3729386174},
{"learn":[0.01912688322],"iteration":693,"passed_time":0.843405455,"remaining_time":0.3718761804},
{"learn":[0.0190810541],"iteration":694,"passed_time":0.8450244611,"remaining_time":0.3708380729},
{"learn":[0.019053505],"iteration":695,"passed_time":0.8464148268,"remaining_time":0.3696984301},
{"learn":[0.0190305705],"iteration":696,"passed_time":0.8477776011,"remaining_time":0.3685460734},
{"learn":[0.01900428066],"iteration":697,"passed_time":0.8486759009,"remaining_time":0.367192152},
{"learn":[0.01898355585],"iteration":698,"passed_time":0.8495842075,"remaining_time":0.3658438433},
{"learn":[0.01895946533],"iteration":699,"passed_time":0.8504044824,"remaining_time":0.3644590639},
{"learn":[0.01892943372],"iteration":700,"passed_time":0.85115969,"remaining_time":0.3630481417},
{"learn":[0.01889307098],"iteration":701,"passed_time":0.8518822331,"remaining_time":0.3616252214},
{"learn":[0.01886851859],"iteration":702,"passed_time":0.8526021416,"remaining_time":0.3602031807},
{"learn":[0.01884746982],"iteration":703,"passed_time":0.8533231813,"remaining_time":0.3587836103},
{"learn":[0.0188415162],"iteration":704,"passed_time":0.8540366976,"remaining_time":0.3573628734},
{"learn":[0.01880779575],"iteration":705,"passed_time":0.8547523816,"remaining_time":0.3559450428},
{"learn":[0.01880076013],"iteration":706,"passed_time":0.8551754269,"remaining_time":0.3544079209},
{"learn":[0.01877156241],"iteration":707,"passed_time":0.8562039422,"remaining_time":0.3531236598},
{"learn":[0.01875253382],"iteration":708,"passed_time":0.8570150069,"remaining_time":0.3517508703},
{"learn":[0.01872237777],"iteration":709,"passed_time":0.8577058741,"remaining_time":0.3503305683},
{"learn":[0.01871666163],"iteration":710,"passed_time":0.8583955269,"remaining_time":0.3489118246},
{"learn":[0.01869266434],"iteration":711,"passed_time":0.8591858049,"remaining_time":0.3475358312},
{"learn":[0.01867925462],"iteration":712,"passed_time":0.8599775151,"remaining_time":0.3461620573},
{"learn":[0.01867723905],"iteration":713,"passed_time":0.8607032136,"remaining_time":0.3447634721},
{"learn":[0.01864940887],"iteration":714,"passed_time":0.8614043798,"remaining_time":0.3433569906},
{"learn":[0.01862987127],"iteration":715,"passed_time":0.8621461563,"remaining_time":0.3419685871},
{"learn":[0.01861425353],"iteration":716,"passed_time":0.8631292346,"remaining_time":0.3406772293},
{"learn":[0.01859111853],"iteration":717,"passed_time":0.8640749803,"remaining_time":0.3393720675},
{"learn":[0.01857228215],"iteration":718,"passed_time":0.8648533026,"remaining_time":0.3380024729},
{"learn":[0.01857074689],"iteration":719,"passed_time":0.8656671485,"remaining_time":0.3366483355},
{"learn":[0.0185471981],"iteration":720,"passed_time":0.8663548013,"remaining_time":0.3352468648},
{"learn":[0.0185146889],"iteration":721,"passed_time":0.8673490007,"remaining_time":0.3339654047},
{"learn":[0.01848717957],"iteration":722,"passed_time":0.8683694403,"remaining_time":0.3326947925},
{"learn":[0.01845979185],"iteration":723,"passed_time":0.8696109482,"remaining_time":0.331509146},
{"learn":[0.01845881548],"iteration":724,"passed_time":0.8709814159,"remaining_time":0.3303722612},
{"learn":[0.01842600625],"iteration":725,"passed_time":0.8722651397,"remaining_time":0.3292019949},
{"learn":[0.01839582384],"iteration":726,"passed_time":0.8731145091,"remaining_time":0.3278683095},
{"learn":[0.01838126858],"iteration":727,"passed_time":0.8739090393,"remaining_time":0.3265154652},
{"learn":[0.01833858151],"iteration":728,"passed_time":0.8746754849,"remaining_time":0.3251537125},
{"learn":[0.01832689962],"iteration":729,"passed_time":0.8753617454,"remaining_time":0.3237639332},
{"learn":[0.01830059774],"iteration":730,"passed_time":0.8760511138,"remaining_time":0.3223772224},
{"learn":[0.01827706796],"iteration":731,"passed_time":0.8767903169,"remaining_time":0.3210106625},
{"learn":[0.01825481454],"iteration":732,"passed_time":0.8777387204,"remaining_time":0.3197220169},
{"learn":[0.01821678256],"iteration":733,"passed_time":0.8785092071,"remaining_time":0.3183698217},
{"learn":[0.01820352961],"iteration":734,"passed_time":0.8792612703,"remaining_time":0.3170125669},
{"learn":[0.01817795096],"iteration":735,"passed_time":0.8799537065,"remaining_time":0.3156355686},
{"learn":[0.01814386336],"iteration":736,"passed_time":0.8806424437,"remaining_time":0.3142591081},
{"learn":[0.01812117103],"iteration":737,"passed_time":0.8816317409,"remaining_time":0.3129912142},
{"learn":[0.01808965905],"iteration":738,"passed_time":0.8824793859,"remaining_time":0.3116740456},
{"learn":[0.01807066497],"iteration":739,"passed_time":0.8832473981,"remaining_time":0.3103301669},
{"learn":[0.01805283259],"iteration":740,"passed_time":0.8848169517,"remaining_time":0.3092680034},
{"learn":[0.01802870456],"iteration":741,"passed_time":0.8856263665,"remaining_time":0.3079401652},
{"learn":[0.01798856033],"iteration":742,"passed_time":0.8863364361,"remaining_time":0.3065793594},
{"learn":[0.01796703642],"iteration":743,"passed_time":0.8870682625,"remaining_time":0.3052277892},
{"learn":[0.0179529466],"iteration":744,"passed_time":0.8877712265,"remaining_time":0.3038680037},
{"learn":[0.01793841668],"iteration":745,"passed_time":0.8885122618,"remaining_time":0.3025229417},
{"learn":[0.01791707569],"iteration":746,"passed_time":0.8892807807,"remaining_time":0.3011888053},
{"learn":[0.01790136681],"iteration":747,"passed_time":0.8899858303,"remaining_time":0.2998347984},
{"learn":[0.01789473896],"iteration":748,"passed_time":0.8906720475,"remaining_time":0.2984762135},
{"learn":[0.01787992587],"iteration":749,"passed_time":0.8913873449,"remaining_time":0.297129115},
{"learn":[0.01785888314],"iteration":750,"passed_time":0.8925587145,"remaining_time":0.2959349133},
{"learn":[0.01783063127],"iteration":751,"passed_time":0.8934190107,"remaining_time":0.2946381844},
{"learn":[0.01782012211],"iteration":752,"passed_time":0.8941334892,"remaining_time":0.2932947833},
{"learn":[0.01781906065],"iteration":753,"passed_time":0.8948773024,"remaining_time":0.2919626212},
{"learn":[0.01777950014],"iteration":754,"passed_time":0.8957715311,"remaining_time":0.290680828},
{"learn":[0.01775312163],"iteration":755,"passed_time":0.8965355766,"remaining_time":0.2893580433},
{"learn":[0.01775208802],"iteration":756,"passed_time":0.8973052989,"remaining_time":0.288038557},
{"learn":[0.01773138991],"iteration":757,"passed_time":0.898108638,"remaining_time":0.2867312538},
{"learn":[0.01771752252],"iteration":758,"passed_time":0.8991683657,"remaining_time":0.2855066879},
{"learn":[0.01769451544],"iteration":759,"passed_time":0.900153464,"remaining_time":0.2842589886},
{"learn":[0.01767912019],"iteration":760,"passed_time":0.9014848892,"remaining_time":0.2831207471},
{"learn":[0.01767267032],"iteration":761,"passed_time":0.9027843841,"remaining_time":0.2819720255},
{"learn":[0.01765512624],"iteration":762,"passed_time":0.9039902207,"remaining_time":0.2807938169},
{"learn":[0.01764653262],"iteration":763,"passed_time":0.9051081399,"remaining_time":0.2795883783},
{"learn":[0.01762559444],"iteration":764,"passed_time":0.9061309651,"remaining_time":0.2783539566},
{"learn":[0.01760703739],"iteration":765,"passed_time":0.9070809119,"remaining_time":0.2770978243},
{"learn":[0.01757905903],"iteration":766,"passed_time":0.9079149035,"remaining_time":0.2758072654},
{"learn":[0.01755058053],"iteration":767,"passed_time":0.9088039155,"remaining_time":0.2745345162},
{"learn":[0.0175382585],"iteration":768,"passed_time":0.9097656492,"remaining_time":0.2732846098},
{"learn":[0.01749990167],"iteration":769,"passed_time":0.9106488189,"remaining_time":0.2720119849},
{"learn":[0.01745601864],"iteration":770,"passed_time":0.9115838401,"remaining_time":0.2707557709},
{"learn":[0.01742319426],"iteration":771,"passed_time":0.9124556876,"remaining_time":0.2694817316},
{"learn":[0.01741988884],"iteration":772,"passed_time":0.9139916376,"remaining_time":0.2684037539},
{"learn":[0.01738274818],"iteration":773,"passed_time":0.9148745129,"remaining_time":0.2671339017},
{"learn":[0.01737503202],"iteration":774,"passed_time":0.9157093189,"remaining_time":0.2658510926},
{"learn":[0.01736145492],"iteration":775,"passed_time":0.9165997142,"remaining_time":0.2645854845},
{"learn":[0.01735231672],"iteration":776,"passed_time":0.9174873485,"remaining_time":0.2633200498},
{"learn":[0.0173185957],"iteration":777,"passed_time":0.918401204,"remaining_time":0.2620630685},
{"learn":[0.01729059522],"iteration":778,"passed_time":0.9192264744,"remaining_time":0.2607818368},
{"learn":[0.01727494016],"iteration":779,"passed_time":0.9209704137,"remaining_time":0.2597608859},
{"learn":[0.01724995986],"iteration":780,"passed_time":0.9225977799,"remaining_time":0.2587053954},
{"learn":[0.01724222469],"iteration":781,"passed_time":0.9241344277,"remaining_time":0.2576231525},
{"learn":[0.01723091449],"iteration":782,"passed_time":0.925965761,"remaining_time":0.2566214178},
{"learn":[0.0172266569],"iteration":783,"passed_time":0.9276093307,"remaining_time":0.255565836},
{"learn":[0.01721535534],"iteration":784,"passed_time":0.92935823,"remaining_time":0.2545376044},
{"learn":[0.01721324329],"iteration":785,"passed_time":0.9303107758,"remaining_time":0.2532907201},
{"learn":[0.01719963194],"iteration":786,"passed_time":0.9312853107,"remaining_time":0.2520505352},
{"learn":[0.01716282522],"iteration":787,"passed_time":0.9322042795,"remaining_time":0.2507960752},
{"learn":[0.01714821857],"iteration":788,"passed_time":0.9331878533,"remaining_time":0.2495597428},
{"learn":[0.01712371488],"iteration":789,"passed_time":0.9353443823,"remaining_time":0.2486358485},
{"learn":[0.01706154741],"iteration":790,"passed_time":0.9370891361,"remaining_time":0.2476000372},
{"learn":[0.01704143342],"iteration":791,"passed_time":0.9379185398,"remaining_time":0.2463220408},
{"learn":[0.01701102636],"iteration":792,"passed_time":0.9387159767,"remaining_time":0.2450368313},
{"learn":[0.01697696487],"iteration":793,"passed_time":0.9395162159,"remaining_time":0.2437535774},
{"learn":[0.01696113759],"iteration":794,"passed_time":0.940336444,"remaining_time":0.2424766931},
{"learn":[0.0169199208],"iteration":795,"passed_time":0.9411797535,"remaining_time":0.2412068715},
{"learn":[0.01689607216],"iteration":796,"passed_time":0.9422813503,"remaining_time":0.2400039073},
{"learn":[0.01685154824],"iteration":797,"passed_time":0.9436566525,"remaining_time":0.238870481},
{"learn":[0.01683159113],"iteration":798,"passed_time":0.9445811381,"remaining_time":0.2376230398},
{"learn":[0.01679370521],"iteration":799,"passed_time":0.9473196313,"remaining_time":0.2368299078},
{"learn":[0.01678960898],"iteration":800,"passed_time":0.9491616613,"remaining_time":0.2358092018},
{"learn":[0.01675924513],"iteration":801,"passed_time":0.9508662192,"remaining_time":0.234752508},
{"learn":[0.01674498268],"iteration":802,"passed_time":0.9527019036,"remaining_time":0.2337263699},
{"learn":[0.01674068085],"iteration":803,"passed_time":0.9567345762,"remaining_time":0.2332338022},
{"learn":[0.01670684095],"iteration":804,"passed_time":0.9585101424,"remaining_time":0.2321856867},
{"learn":[0.01669241489],"iteration":805,"passed_time":0.9601695022,"remaining_time":0.2311077958},
{"learn":[0.01666311819],"iteration":806,"passed_time":0.9626313578,"remaining_time":0.2302203867},
{"learn":[0.01664724558],"iteration":807,"passed_time":0.9643319179,"remaining_time":0.2291481785},
{"learn":[0.01662236681],"iteration":808,"passed_time":0.9680730584,"remaining_time":0.2285561856},
{"learn":[0.01658048196],"iteration":809,"passed_time":0.9701828392,"remaining_time":0.2275737524},
{"learn":[0.01655876947],"iteration":810,"passed_time":0.9712519247,"remaining_time":0.2263460096},
{"learn":[0.01653945343],"iteration":811,"passed_time":0.9731842476,"remaining_time":0.2253185204},
{"learn":[0.0165364027],"iteration":812,"passed_time":0.9751241772,"remaining_time":0.2242905549},
{"learn":[0.0165252155],"iteration":813,"passed_time":0.9783663174,"remaining_time":0.2235579054},
{"learn":[0.01650294296],"iteration":814,"passed_time":0.9798905629,"remaining_time":0.2224291462},
{"learn":[0.01649872625],"iteration":815,"passed_time":0.980756048,"remaining_time":0.2211508736},
{"learn":[0.01647384928],"iteration":816,"passed_time":0.9817269495,"remaining_time":0.2198972237},
{"learn":[0.01644782491],"iteration":817,"passed_time":0.9832860108,"remaining_time":0.2187751271},
{"learn":[0.01643202046],"iteration":818,"passed_time":0.9842519723,"remaining_time":0.2175208876},
{"learn":[0.01641568684],"iteration":819,"passed_time":0.9853681126,"remaining_time":0.2163003174},
{"learn":[0.01638649473],"iteration":820,"passed_time":0.9883859756,"remaining_time":0.215494628},
{"learn":[0.01636607522],"iteration":821,"passed_time":0.9913483081,"remaining_time":0.2146715314},
{"learn":[0.01633836859],"iteration":822,"passed_time":0.9926034906,"remaining_time":0.2134760848},
{"learn":[0.01631840448],"iteration":823,"passed_time":0.9945694515,"remaining_time":0.21243231},
{"learn":[0.01630391652],"iteration":824,"passed_time":0.9957406255,"remaining_time":0.2112177084},
{"learn":[0.01630289566],"iteration":825,"passed_time":0.9967054914,"remaining_time":0.2099597524},
{"learn":[0.01627535631],"iteration":826,"passed_time":0.9975323441,"remaining_time":0.2086736342},
{"learn":[0.01625340235],"iteration":827,"passed_time":0.9984729875,"remaining_time":0.2074122631},
{"learn":[0.0162249538],"iteration":828,"passed_time":0.9993137536,"remaining_time":0.2061310638},
{"learn":[0.0162085914],"iteration":829,"passed_time":1.001065821,"remaining_time":0.2050375777},
{"learn":[0.01620183381],"iteration":830,"passed_time":1.003089085,"remaining_time":0.20399766},
{"learn":[0.01619766132],"iteration":831,"passed_time":1.004491139,"remaining_time":0.2028299415},
{"learn":[0.01617969125],"iteration":832,"passed_time":1.008274546,"remaining_time":0.2021390747},
{"learn":[0.01615693528],"iteration":833,"passed_time":1.009457007,"remaining_time":0.2009230973},
{"learn":[0.01614818073],"iteration":834,"passed_time":1.010825624,"remaining_time":0.1997439855},
{"learn":[0.01613504801],"iteration":835,"passed_time":1.011657111,"remaining_time":0.1984590505},
{"learn":[0.01610377912],"iteration":836,"passed_time":1.01241682,"remaining_time":0.1971612206},
{"learn":[0.01607829624],"iteration":837,"passed_time":1.013171863,"remaining_time":0.195863773},
{"learn":[0.01605074195],"iteration":838,"passed_time":1.013915284,"remaining_time":0.1945653882},
{"learn":[0.01602680459],"iteration":839,"passed_time":1.014693691,"remaining_time":0.1932749887},
{"learn":[0.01598819752],"iteration":840,"passed_time":1.01556807,"remaining_time":0.1920039515},
{"learn":[0.01596815982],"iteration":841,"passed_time":1.016717973,"remaining_time":0.1907855579},
{"learn":[0.01596122889],"iteration":842,"passed_time":1.019113192,"remaining_time":0.1897992539},
{"learn":[0.01593648535],"iteration":843,"passed_time":1.020166769,"remaining_time":0.1885616303},
{"learn":[0.01591860446],"iteration":844,"passed_time":1.021139296,"remaining_time":0.187309575},
{"learn":[0.01591164417],"iteration":845,"passed_time":1.022654134,"remaining_time":0.1861568991},
{"learn":[0.01589692711],"iteration":846,"passed_time":1.023829235,"remaining_time":0.1849419987},
{"learn":[0.01585697756],"iteration":847,"passed_time":1.024562599,"remaining_time":0.183648013},
{"learn":[0.01583091306],"iteration":848,"passed_time":1.025451896,"remaining_time":0.1823830817},
{"learn":[0.01582032461],"iteration":849,"passed_time":1.026248613,"remaining_time":0.1811026965},
{"learn":[0.01580303686],"iteration":850,"passed_time":1.027360608,"remaining_time":0.1798786493},
{"learn":[0.01579953784],"iteration":851,"passed_time":1.02862474,"remaining_time":0.1786812929},
{"learn":[0.01579011846],"iteration":852,"passed_time":1.031760643,"remaining_time":0.1778063477},
{"learn":[0.01578753463],"iteration":853,"passed_time":1.033987659,"remaining_time":0.176770724},
{"learn":[0.01578393827],"iteration":854,"passed_time":1.035190985,"remaining_time":0.175558705},
{"learn":[0.01575536798],"iteration":855,"passed_time":1.036701641,"remaining_time":0.1743984069},
{"learn":[0.01574941773],"iteration":856,"passed_time":1.037545643,"remaining_time":0.1731260524},
{"learn":[0.01572509007],"iteration":857,"passed_time":1.038316891,"remaining_time":0.1718426556},
{"learn":[0.01570561554],"iteration":858,"passed_time":1.039088954,"remaining_time":0.170560585},
{"learn":[0.01570466069],"iteration":859,"passed_time":1.039791873,"remaining_time":0.1692684444},
{"learn":[0.01569182737],"iteration":860,"passed_time":1.040757628,"remaining_time":0.1680201049},
{"learn":[0.01567080257],"iteration":861,"passed_time":1.041534137,"remaining_time":0.1667421241},
{"learn":[0.01565314735],"iteration":862,"passed_time":1.042305683,"remaining_time":0.1654645175},
{"learn":[0.01565182419],"iteration":863,"passed_time":1.043022839,"remaining_time":0.164179521},
{"learn":[0.01564343464],"iteration":864,"passed_time":1.044200944,"remaining_time":0.1629677775},
{"learn":[0.01563622894],"iteration":865,"passed_time":1.045117719,"remaining_time":0.1617156747},
{"learn":[0.01563413644],"iteration":866,"passed_time":1.046925723,"remaining_time":0.1606010625},
{"learn":[0.01560129265],"iteration":867,"passed_time":1.047956213,"remaining_time":0.159366613},
{"learn":[0.01557837948],"iteration":868,"passed_time":1.049709879,"remaining_time":0.1582416503},
{"learn":[0.01556765854],"iteration":869,"passed_time":1.050865585,"remaining_time":0.157025892},
{"learn":[0.01555015773],"iteration":870,"passed_time":1.051649111,"remaining_time":0.1557551496},
{"learn":[0.01553935255],"iteration":871,"passed_time":1.052550301,"remaining_time":0.1545027964},
{"learn":[0.01552898174],"iteration":872,"passed_time":1.053471149,"remaining_time":0.1532541076},
{"learn":[0.01550462913],"iteration":873,"passed_time":1.054236359,"remaining_time":0.1519837314},
{"learn":[0.01549078232],"iteration":874,"passed_time":1.055004764,"remaining_time":0.1507149663},
{"learn":[0.01548291657],"iteration":875,"passed_time":1.055759366,"remaining_time":0.1494453897},
{"learn":[0.01546818005],"iteration":876,"passed_time":1.056675453,"remaining_time":0.1481996359},
{"learn":[0.01544771515],"iteration":877,"passed_time":1.057411269,"remaining_time":0.1469295841},
{"learn":[0.01541974172],"iteration":878,"passed_time":1.058335401,"remaining_time":0.1456866707},
{"learn":[0.01540486472],"iteration":879,"passed_time":1.061702702,"remaining_time":0.1447776412},
{"learn":[0.01538536495],"iteration":880,"passed_time":1.063600547,"remaining_time":0.1436645461},
{"learn":[0.01536476008],"iteration":881,"passed_time":1.065856947,"remaining_time":0.1425976414},
{"learn":[0.01535100886],"iteration":882,"passed_time":1.067101814,"remaining_time":0.1413940116},
{"learn":[0.0153375433],"iteration":883,"passed_time":1.067966037,"remaining_time":0.1401403397},
{"learn":[0.01531530129],"iteration":884,"passed_time":1.06875363,"remaining_time":0.1388775904},
{"learn":[0.01529617924],"iteration":885,"passed_time":1.06961092,"remaining_time":0.1376248813},
{"learn":[0.01526957121],"iteration":886,"passed_time":1.070391001,"remaining_time":0.1363632278},
{"learn":[0.01524771564],"iteration":887,"passed_time":1.071237947,"remaining_time":0.1351110924},
{"learn":[0.01522637131],"iteration":888,"passed_time":1.071976169,"remaining_time":0.1338462933},
{"learn":[0.01520793642],"iteration":889,"passed_time":1.072908525,"remaining_time":0.1326066716},
{"learn":[0.01520062302],"iteration":890,"passed_time":1.074583499,"remaining_time":0.1314585874},
{"learn":[0.01518990244],"iteration":891,"passed_time":1.076163524,"remaining_time":0.1302978258},
{"learn":[0.01518746263],"iteration":892,"passed_time":1.077035889,"remaining_time":0.1290513327},
{"learn":[0.01516859597],"iteration":893,"passed_time":1.0784277,"remaining_time":0.1278672665},
{"learn":[0.01514349504],"iteration":894,"passed_time":1.079417309,"remaining_time":0.1266355502},
{"learn":[0.01513036743],"iteration":895,"passed_time":1.080886815,"remaining_time":0.1254600767},
{"learn":[0.01510756944],"iteration":896,"passed_time":1.082374542,"remaining_time":0.12428604},
{"learn":[0.01507594544],"iteration":897,"passed_time":1.08341045,"remaining_time":0.1230599843},
{"learn":[0.01505297985],"iteration":898,"passed_time":1.08433925,"remaining_time":0.1218223184},
{"learn":[0.01504013424],"iteration":899,"passed_time":1.085124167,"remaining_time":0.1205693518},
{"learn":[0.01503495231],"iteration":900,"passed_time":1.085917059,"remaining_time":0.1193183006},
{"learn":[0.01501817603],"iteration":901,"passed_time":1.086864336,"remaining_time":0.1180850387},
{"learn":[0.01501314165],"iteration":902,"passed_time":1.088172232,"remaining_time":0.1168911478},
{"learn":[0.01497776625],"iteration":903,"passed_time":1.089404835,"remaining_time":0.1156890091},
{"learn":[0.01496301196],"iteration":904,"passed_time":1.090921643,"remaining_time":0.1145166366},
{"learn":[0.01495481828],"iteration":905,"passed_time":1.092331635,"remaining_time":0.1133324213},
{"learn":[0.01493986948],"iteration":906,"passed_time":1.093560529,"remaining_time":0.1121291391},
{"learn":[0.0149076414],"iteration":907,"passed_time":1.094329655,"remaining_time":0.1108792162},
{"learn":[0.01488126646],"iteration":908,"passed_time":1.095135804,"remaining_time":0.1096340573},
{"learn":[0.0148659835],"iteration":909,"passed_time":1.095931764,"remaining_time":0.1083888558},
{"learn":[0.01483778371],"iteration":910,"passed_time":1.096719282,"remaining_time":0.1071438157},
{"learn":[0.01482270806],"iteration":911,"passed_time":1.09745969,"remaining_time":0.1058952333},
{"learn":[0.01481793837],"iteration":912,"passed_time":1.098139073,"remaining_time":0.1046419489},
{"learn":[0.0147997509],"iteration":913,"passed_time":1.098881456,"remaining_time":0.1033958482},
{"learn":[0.01477324695],"iteration":914,"passed_time":1.099613904,"remaining_time":0.1021499255},
{"learn":[0.01475666047],"iteration":915,"passed_time":1.100323751,"remaining_time":0.1009030514},
{"learn":[0.01474396488],"iteration":916,"passed_time":1.101097648,"remaining_time":0.09966314588},
{"learn":[0.01473097318],"iteration":917,"passed_time":1.102429742,"remaining_time":0.09847411638},
{"learn":[0.01471310222],"iteration":918,"passed_time":1.10388101,"remaining_time":0.09729527947},
{"learn":[0.01470652573],"iteration":919,"passed_time":1.105190654,"remaining_time":0.09610353515},
{"learn":[0.01468488371],"iteration":920,"passed_time":1.106214292,"remaining_time":0.09488700221},
{"learn":[0.01466967389],"iteration":921,"passed_time":1.108451993,"remaining_time":0.09377359597},
{"learn":[0.01464138474],"iteration":922,"passed_time":1.10967126,"remaining_time":0.092572792},
{"learn":[0.01462833546],"iteration":923,"passed_time":1.111214346,"remaining_time":0.09139858254},
{"learn":[0.01461342028],"iteration":924,"passed_time":1.111996804,"remaining_time":0.09016190299},
{"learn":[0.01459503567],"iteration":925,"passed_time":1.112730805,"remaining_time":0.08892233219},
{"learn":[0.01456360492],"iteration":926,"passed_time":1.113671467,"remaining_time":0.08770012629},
{"learn":[0.0145538253],"iteration":927,"passed_time":1.114488037,"remaining_time":0.08646889943},
{"learn":[0.0145359297],"iteration":928,"passed_time":1.115535042,"remaining_time":0.08525617655},
{"learn":[0.01451216238],"iteration":929,"passed_time":1.116579129,"remaining_time":0.08404359035},
{"learn":[0.01450175955],"iteration":930,"passed_time":1.11769848,"remaining_time":0.0828369443},
{"learn":[0.01447589874],"iteration":931,"passed_time":1.11945873,"remaining_time":0.08167724638},
{"learn":[0.01445765572],"iteration":932,"passed_time":1.120975006,"remaining_time":0.08049874108},
{"learn":[0.01445204936],"iteration":933,"passed_time":1.122651691,"remaining_time":0.07933084752},
{"learn":[0.01444235289],"iteration":934,"passed_time":1.123548939,"remaining_time":0.07810768028},
{"learn":[0.01444001958],"iteration":935,"passed_time":1.124362489,"remaining_time":0.0768794864},
{"learn":[0.01443872697],"iteration":936,"passed_time":1.125160944,"remaining_time":0.07565116275},
{"learn":[0.0144177966],"iteration":937,"passed_time":1.125913892,"remaining_time":0.07442074767},
{"learn":[0.01439207153],"iteration":938,"passed_time":1.126630301,"remaining_time":0.07318897587},
{"learn":[0.01438104688],"iteration":939,"passed_time":1.127344144,"remaining_time":0.07195813683},
{"learn":[0.01437582086],"iteration":940,"passed_time":1.128044351,"remaining_time":0.07072754166},
{"learn":[0.01437261815],"iteration":941,"passed_time":1.128742475,"remaining_time":0.06949794431},
{"learn":[0.01437176437],"iteration":942,"passed_time":1.129517028,"remaining_time":0.06827409397},
{"learn":[0.01436537757],"iteration":943,"passed_time":1.130412327,"remaining_time":0.06705835838},
{"learn":[0.01434021152],"iteration":944,"passed_time":1.132060056,"remaining_time":0.06588709318},
{"learn":[0.01432146198],"iteration":945,"passed_time":1.133504489,"remaining_time":0.06470321609},
{"learn":[0.01430076241],"iteration":946,"passed_time":1.134288271,"remaining_time":0.06348181451},
{"learn":[0.01429075947],"iteration":947,"passed_time":1.135077986,"remaining_time":0.0622616617},
{"learn":[0.01428573216],"iteration":948,"passed_time":1.135830124,"remaining_time":0.06104039655},
{"learn":[0.01426881279],"iteration":949,"passed_time":1.136796639,"remaining_time":0.05983140204},
{"learn":[0.01424945244],"iteration":950,"passed_time":1.137758785,"remaining_time":0.05862269237},
{"learn":[0.01424637473],"iteration":951,"passed_time":1.138569447,"remaining_time":0.05740686288},
{"learn":[0.01424553107],"iteration":952,"passed_time":1.139334392,"remaining_time":0.05618962897},
{"learn":[0.01424337051],"iteration":953,"passed_time":1.140144459,"remaining_time":0.05497551897},
{"learn":[0.01422104934],"iteration":954,"passed_time":1.140939727,"remaining_time":0.0537615578},
{"learn":[0.01420623019],"iteration":955,"passed_time":1.141636379,"remaining_time":0.05254393378},
{"learn":[0.01418086417],"iteration":956,"passed_time":1.142348781,"remaining_time":0.05132810616},
{"learn":[0.01416532331],"iteration":957,"passed_time":1.14324737,"remaining_time":0.05012149221},
{"learn":[0.01414395886],"iteration":958,"passed_time":1.144113566,"remaining_time":0.04891413578},
{"learn":[0.01412491502],"iteration":959,"passed_time":1.144944748,"remaining_time":0.04770603116},
{"learn":[0.01412035254],"iteration":960,"passed_time":1.1458672,"remaining_time":0.04650241499},
{"learn":[0.01409311699],"iteration":961,"passed_time":1.148441619,"remaining_time":0.04536463775},
{"learn":[0.01407858086],"iteration":962,"passed_time":1.150638858,"remaining_time":0.04420938499},
{"learn":[0.01405976333],"iteration":963,"passed_time":1.152588778,"remaining_time":0.04304273443},
{"learn":[0.01404722485],"iteration":964,"passed_time":1.153681929,"remaining_time":0.04184338602},
{"learn":[0.01403242726],"iteration":965,"passed_time":1.154775688,"remaining_time":0.04064427887},
{"learn":[0.01402958834],"iteration":966,"passed_time":1.155629004,"remaining_time":0.03943718422},
{"learn":[0.0140194047],"iteration":967,"passed_time":1.156430063,"remaining_time":0.038229093},
{"learn":[0.01400581738],"iteration":968,"passed_time":1.157248174,"remaining_time":0.03702238739},
{"learn":[0.01399340492],"iteration":969,"passed_time":1.15825751,"remaining_time":0.03582239721},
{"learn":[0.01398867746],"iteration":970,"passed_time":1.159322308,"remaining_time":0.03462445615},
{"learn":[0.01398397895],"iteration":971,"passed_time":1.160278019,"remaining_time":0.03342364664},
{"learn":[0.01395795539],"iteration":972,"passed_time":1.161906766,"remaining_time":0.03224201715},
{"learn":[0.01394589238],"iteration":973,"passed_time":1.166307666,"remaining_time":0.03113346952},
{"learn":[0.01391685648],"iteration":974,"passed_time":1.167866129,"remaining_time":0.02994528537},
{"learn":[0.01389845343],"iteration":975,"passed_time":1.168864501,"remaining_time":0.0287425697},
{"learn":[0.01387965004],"iteration":976,"passed_time":1.169858217,"remaining_time":0.02754016274},
{"learn":[0.01387873806],"iteration":977,"passed_time":1.170671742,"remaining_time":0.02633412917},
{"learn":[0.0138733259],"iteration":978,"passed_time":1.171439534,"remaining_time":0.02512791646},
{"learn":[0.01386197621],"iteration":979,"passed_time":1.172406249,"remaining_time":0.02392665814},
{"learn":[0.01385384258],"iteration":980,"passed_time":1.174089749,"remaining_time":0.02273976068},
{"learn":[0.01383791542],"iteration":981,"passed_time":1.17520387,"remaining_time":0.02154141514},
{"learn":[0.01383241824],"iteration":982,"passed_time":1.176750377,"remaining_time":0.02035071863},
{"learn":[0.01383154192],"iteration":983,"passed_time":1.178747002,"remaining_time":0.01916661791},
{"learn":[0.01380406352],"iteration":984,"passed_time":1.179954163,"remaining_time":0.01796884512},
{"learn":[0.01378869784],"iteration":985,"passed_time":1.180819336,"remaining_time":0.01676619746},
{"learn":[0.01375991379],"iteration":986,"passed_time":1.181638036,"remaining_time":0.01556362155},
{"learn":[0.01372985478],"iteration":987,"passed_time":1.182425003,"remaining_time":0.01436143728},
{"learn":[0.01372924241],"iteration":988,"passed_time":1.183128222,"remaining_time":0.01315916122},
{"learn":[0.01372694968],"iteration":989,"passed_time":1.183825991,"remaining_time":0.01195783829},
{"learn":[0.01372062816],"iteration":990,"passed_time":1.184860564,"remaining_time":0.01076059039},
{"learn":[0.01370742064],"iteration":991,"passed_time":1.186014248,"remaining_time":0.009564631029},
{"learn":[0.0136883183],"iteration":992,"passed_time":1.187508556,"remaining_time":0.008371158},
{"learn":[0.01367979395],"iteration":993,"passed_time":1.188859356,"remaining_time":0.007176213417},
{"learn":[0.01366916548],"iteration":994,"passed_time":1.192096343,"remaining_time":0.005990433884},
{"learn":[0.01365965804],"iteration":995,"passed_time":1.193897076,"remaining_time":0.004794767373},
{"learn":[0.01363782666],"iteration":996,"passed_time":1.194802256,"remaining_time":0.003595192344},
{"learn":[0.0136169463],"iteration":997,"passed_time":1.195620337,"remaining_time":0.00239603274},
{"learn":[0.01359878239],"iteration":998,"passed_time":1.196417821,"remaining_time":0.001197615436},
{"learn":[0.01359666536],"iteration":999,"passed_time":1.197225302,"remaining_time":0}
]}